Workbook

Sheet PF 2025
A2: EMPRESA | B2: PREVISÃO ORÇAMENTÁRIA - DIAMOND TOWER | F2: MARÇO | G2: ABRIL | H2: MAIO | I2: JUNHO | J2: JULHO | K2: AGOSTO | L2: SETEMBRO | M2: OUTUBRO | N2: NOVEMBRO | O2: DEZEMBRO | P2: JANEIRO | Q2: FEVEREIRO | R2: MARÇO | T2: PREVISTO | U2: REALIZADO
B3: CONTRATOS MÃO DE OBRA | C3: DATA | D3: ÍNDICE | E3: =SUM(E4:E14) | F3: =SUM(F4:F21) | G3: =SUM(G4:G21) | H3: =SUM(H4:H21) | I3: =SUM(I4:I21) | J3: =SUM(J4:J21) | K3: =SUM(K4:K21) | L3: =SUM(L4:L21) | M3: =SUM(M4:M21) | ... R3: =SUM(R4:R21) | T3: =SUM(T4:T21) | U3: =SUM(U4:U21)
A4: ALTO PADRÃO | B4: Monitoramento - 01 Posto 24h - Central de Segurança | C4: MARÇO | D4: DISSÍDIO | E4: 119800 | F4: =5574.93+94647.29+11276.34 | G4: 192694.98 | T4: =E4*11 | U4: =SUM(H4:R10)
B5: Ronda Vigilante - 01 Posto 24h
B6: Porteiro 02 postos 8h - (Seg à Dom - das 7h as 22h)
B7: Expedição 01 posto 8h - (Seg à Sáb - das 08h às 16h20)
B8: Recepção - 04 postos 8h (das 7h as 22h)
B9: Limpeza - 03 Postos 44h semanais
B10: Serviços Gerais – 01 posto 44h semanais
A11: CAPPELLETTO | B11: 02 Gestores presenciais (Administrativo e Operacional) | C11: SETEMBRO | D11: IPCA (6,5%) | E11: 24900 | F11: =16992.72+318.15 | G11: 48903.6
A12: GUARIDA | B12: Auxiliar Administração | C12: NOVEMBRO | D12: IPCA (6,5%) | E12: =2835*1.065 | F12: =2.1+1139.05+0.95+78.75+59.007+269.05+1498.9 | G12: 2997.8 | T12: =E12*12 | U12: =SUM(F12:R12)
A13: ORGÂNICO | B13: Oficial Manutenção - 01 Posto 44h semanais | C13: ANUAL | D13: DISSÍDIO | E13: 8500 | F13: =48.38+48.38+475.68+512.88+1189.22+59.46+148.65+11.89+89.19+17.83+69.33+59.46+570.44+175.32+211.2+900+384 | G13: 4586.66 | T13: =E13*11 | U13: =SUM(F13:R13)
A14: ORGÂNICO | B14: Remuneração Subsíndico | C14: ANUAL | D14: SAL. MÍN. REG. | E14: 8500 | F14: =7206.2+890.65+1619.37 | T14: =E14*12 | U14: =SUM(F14:R14)
B16: MANUTENÇÕES/LOCAÇÕES - CONTRATOS | E16: =SUM(E17:E21) | F16: =SUM(F17:F19) | G16: =SUM(G17:G19) | H16: =SUM(H17:H19) | I16: =SUM(I17:I19) | J16: =SUM(J17:J19) | K16: =SUM(K17:K19) | L16: =SUM(L17:L19) | M16: =SUM(M17:M19) | ... R16: =SUM(R17:R19) | T16: =SUM(T17:T20) | U16: =SUM(U17:U20)
A17: FG PISCINAS | B17: Limpeza Espelho D'água, Química e AFT com Material | C17: INDEFINIDO | D17: IGP-M | E17: =850*1.049 | F17: =6.46+14.85+898.7 | G17: 3297.16 | T17: =E17*12 | U17: =SUM(F17:R17)
A18: ELITE | B18: Manutenção Preventiva Elevadores (7) - Com Peças - Atlas | C18: MAIO | D18: IGP-DI | E18: =(9223.61*1.049)-4307.45 | F18: =2777.9+461.18+4.17+2777.9+8333.53 | G18: 59721.6 | T18: =E18*12 | U18: =SUM(F18:R18)
A19: STEMAC | B19: Manutenção preventiva motor gerador | C19: JANEIRO | D19: IGP-M | E19: 1472 | F19: =73.58+22+1167.75+161.88 | G19: 2391.56 | T19: =E19*12 | U19: =SUM(F19:R19)
A20: BELLINI | B20: Consultoria jurídica | C20: INDEFINIDO | D20: SAL.MÍN. NAC. | E20: 3020 | F20: =2958.58+77.42 | G20: 5920.2 | T20: =E20*12 | U20: =SUM(F20:R20)
A21: AUDI PASTAS | B21: Auditoria Externa | C21: OUTUBRO | D21: IPCA (6,5%) | E21: =1330*1.065 | F21: =26.6+1303.4 | G21: 2606.8 | T21: =E21*12 | U21: =SUM(F21:R21)
B23: MANUTENÇÕES - SEM CONTRATO | E23: =SUM(E24:E32) | F23: =SUM(F24:F32) | G23: =SUM(G24:G32) | H23: =SUM(H24:H32) | I23: =SUM(I24:I32) | J23: =SUM(J24:J32) | K23: =SUM(K24:K32) | L23: =SUM(L24:L32) | ... R23: =SUM(R24:R32) | T23: =SUM(T24:T32) | U23: =SUM(U24:U32)
A24: MULTIPLAN | B24: Lixo/Entulho/Manutenção Externa - Despesa Compartilhada | E24: =3000*1.065 | T24: =E24*12 | U24: =SUM(F24:R24)
A25: ALPINISMO | B25: Limpeza da Fachada | E25: 8350 | G25: 8285.9 | T25: =E25*12 | U25: =SUM(F25:R25)
A26: DEMANDA | B26: Manutenção Bombas de Recalque | E26: 525 | G26: 880 | T26: =E26*12 | U26: =SUM(F26:R26)
B27: Manutenção Interfones | E27: 500 | F27: =275.87+9.8+9.8 | G27: 775.96 | T27: =E27*12 | U27: =SUM(F27:R27)
B28: Manutenção Predial | E28: 4000 | F28: =1361.99+243.21+3360+535.07+950+800+486+520+2400 | G28: 5803.98 | T28: =E28*12 | U28: =SUM(F28:R28)
B29: Manutenção Preventiva Sistema de Incêndio | E29: 350 | T29: =E29*12 | U29: =SUM(F29:R29)
B30: Obrigações Legais (AFT, certificado de qualidade do ar de ambiente climatizado, certificado digital, inspeção da esccada pressurizada, laudo de potabilidade, teste mangueiras, recarga extintores, SPDA, subestação de energia) | E30: 3200 | F30: =4160.26+171.04+33.58+266.62+102.9+736.7 | G30: 2142.1 | T30: =E30*12 | U30: =SUM(F30:R30)
B31: Controle Pragas e Limpeza Caixa D'água (2x ano) | E31: 525 | F31: =826.33 | G31: 1663.66 | T31: =E31*12 | U31: =SUM(F31:R31)
B32: Paisagismo interno | E32: 105 | T32: =E32*12 | U32: =SUM(F32:R32)
B34: MATERIAIS E EQUIPAMENTOS | E34: =SUM(E35:E46) | F34: =SUM(F35:F46) | G34: =SUM(G35:G46) | H34: =SUM(H35:H46) | I34: =SUM(I35:I46) | J34: =SUM(J35:J46) | K34: =SUM(K35:K46) | L34: =SUM(L35:L46) | ... R34: =SUM(R35:R46) | T34: =SUM(T35:T46) | U34: =SUM(U35:U46)
B35: Chaveiro | E35: 20 | G35: 960 | T35: =E35*12 | U35: =SUM(F35:R35)
B36: Lâmpadas | E36: 500 | T36: =E36*12 | U36: =SUM(F36:R36)
B37: Materiais/Serviços Obras Diversas (Alvenaria, Serralheria, Funilaria, Outros) | E37: 1500 | F37: =545+136.8 | G37: 1260.8 | T37: =E37*12 | U37: =SUM(F37:R37)
B38: Material de Ferragem (Elétrica, Hidráulica e Ferramentas) | E38: 2000 | F38: =540.2+285+63.4+269.05+93.9+288.3+485.95+32 | G38: 12050.62 | T38: =E38*12 | U38: =SUM(F38:R38)
B39: Material Expediente Interno | E39: 500 | F39: =99+290.14 | G39: 538.1 | T39: =E39*12 | U39: =SUM(F39:R39)
B40: Material Limpeza/Consumíveis | E40: 2000 | F40: =763.81+662.23 | G40: 2142.24 | T40: =E40*12 | U40: =SUM(F40:R40)
A41: ELITE | B41: Peças elevador | E41: 700 | F41: =542.1+79.18 | T41: =E41*12 | U41: =SUM(F41:R41)
A42: DEMANDA | B42: Móveis e Utensílios | E42: 600 | G42: 8888.84 | T42: =E42*12 | U42: =SUM(F42:R42)
B43: Peças Ar Condicionado/Exaustores | E43: 525 | F43: =1421+1558.2 | T43: =E43*12 | U43: =SUM(F43:R43)
B44: Peças de reposição para extintores e hidrantes e recargas eventuais | E44: 150 | T44: =E44*12 | U44: =SUM(F44:R44)
B45: Peças para Grupo Gerador, limpeza semestral filtro e óleo e óleo diesel | E45: 500 | F45: =1500 | T45: =E45*12 | U45: =SUM(F45:R45)
B46: Peças para manutenção das catracas | E46: 350 | T46: =E46*12 | U46: =SUM(F46:R46)
B48: DESPESAS ADMINISTRATIVAS | E48: =SUM(E49:E54) | F48: =SUM(F49:F53) | G48: =SUM(G49:G53) | H48: =SUM(H49:H53) | I48: =SUM(I49:I53) | J48: =SUM(J49:J53) | K48: =SUM(K49:K53) | L48: =SUM(L49:L53) | M48: =SUM(M49:M53) | ... R48: =SUM(R49:R53) | T48: =SUM(T49:T54) | U48: =SUM(U49:U54)
B49: Telefonia/Internet- apenas telefone, internet comodato | E49: 250 | F49: =101.12+39.9 | G49: 202.24 | T49: =E49*12 | U49: =SUM(F49:R49)
B50: Correio/Remessa Correspondências/Motoboy/Diversas | E50: 150 | T50: =E50*12 | U50: =SUM(F50:R50)
B51: Impostos - DIRF/DARF/ISSQN/PIS/COFINS | E51: 170 | F51: =87.5+589.26 | G51: 37811.92 | T51: =E51*12 | U51: =SUM(F51:R51)
B52: Taxa Desepesas com Assembleia | E52: 150 | F52: =750 | G52: 576 | T52: =E52*12 | U52: =SUM(F52:R52)
B53: Custas Judiciais | E53: 200 | T53: =E53*12 | U53: =SUM(F53:R53)
A54: GOOGLE | B54: Hospedagem / Domínio Corporativo | E54: 200 | F54: =937.29 | T54: =E54*12 | U54: =SUM(F54:R54)
B56: COTA | E56: =E3+E16+E23+E34+E48 | F56: =SUM(F3,F16,F23,F34,F48) | G56: =SUM(G3,G16,G23,G34,G48) | H56: =SUM(H3,H16,H23,H34,H48) | I56: =SUM(I3,I16,I23,I34,I48) | J56: =SUM(J3,J16,J23,J34,J48) | K56: =SUM(K3,K16,K23,K34,K48) | L56: =SUM(L3,L16,L23,L34,L48) | M56: =SUM(M3,M16,M23,M34,M48) | ... R56: =SUM(R3,R16,R23,R34,R48) | T56: =E56*12 | U56: =U3+U16+U23+U34+U48
B58: DESPESAS VARIÁVEIS | E58: R$ - | F58: =SUM(F59:F61) | G58: =SUM(G59:G61) | H58: =SUM(H59:H61) | I58: =SUM(I59:I61) | J58: =SUM(J59:J61) | K58: =SUM(K59:K61) | L58: =SUM(L59:L61) | M58: =SUM(M59:M61) | ... R58: =SUM(R59:R61) | T58: =SUM(T59:T61) | U58: =SUM(U59:U61)
B59: Água e Esgoto - Área Comum | E59: - | F59: =12193.65 | G59: 21858.98 | U59: =SUM(F59:R59)
B60: Energia Elétrica - Área Comum | E60: - | F60: =22998.81 | G60: 50569.68 | U60: =SUM(F60:R60)
B61: Seguro fogo | E61: - | G61: 96.76 | U61: =SUM(F61:R61)
B63: OUTRAS DESPESAS | E63: R$ - | F63: =SUM(F64:F68) | G63: =SUM(G64:G68) | H63: =SUM(H64:H68) | I63: =SUM(I64:I68) | J63: =SUM(J64:J68) | K63: =SUM(K64:K68) | L63: =SUM(L64:L68) | M63: =SUM(M64:M68) | ... R63: =SUM(R64:R68) | T63: =SUM(T64:T67) | U63: =SUM(U64:U68)
B64: Despesas Não Orçadas | E64: - | U64: =SUM(F64:R64)
B65: Despesas reembolsáveis | F65: =280 | G65: 6701.56 | T65: =E65*12 | U65: =SUM(F65:R65)
B66: Honorários advocatícios | F66: =974.5+63.75+63.75+25.5+2437.5+2437.5 | T66: =E66*12 | U66: =SUM(F66:R66)
B67: Ampliação do CFTV | T67: =E67*12 | U67: =SUM(F67:R67)
B68: Transferências Entre Contas | E68: - | G68: 128.88
B70: TOTAL DESPESAS CONTA PRINCIPAL | E70: =E56 | F70: =F63+F58+F56 | G70: =G63+G58+G56 | H70: =H63+H58+H56 | I70: =I63+I58+I56 | J70: =J63+J58+J56 | K70: =K63+K58+K56 | L70: =L63+L58+L56 | M70: =M63+M58+M56 | ... O70: =O63+O58+O56 | P70: =P56+P58+P63 | Q70: =Q56+Q58+Q63 | R70: =R63+R58+R56 | T70: =T56+T58+T63 | U70: =U56+U58+U63

Sheet RS 2025
C2: RESUMO DE SALDOS
C3: 2025 | O3: 2026
B4: CONTA | C4: MARÇO | D4: ABRIL | E4: MAIO | F4: JUNHO | G4: JULHO | H4: AGOSTO | I4: SETEMBRO | J4: OUTUBRO | K4: NOVEMBRO | L4: DEZEMBRO | M4: JANEIRO | N4: FEVEREIRO | O4: MARÇO
B6: PRINCIPAL | C6: =C10 | D6: =D10 | E6: =E10 | F6: =F10 | G6: =G10 | H6: =H10 | I6: =I10 | J6: =J10 | ... O6: =O10
B7: SALDO ANTERIOR | C7: -360002.73 | D7: =C10 | E7: =D10 | F7: =E10 | G7: =F10 | H7: =G10 | I7: =H10 | J7: =I10 | K7: =J10 | ... O7: =N10
B8: RECEITA | C8: 217637.03 | D8: 329553.04 | E8: 232347.35 | F8: 238638.6 | G8: 268148.15 | H8: 259788.93
B9: DESPESA | C9: -239150.34 | D9: -262247.69 | E9: =-290588.22-5052.13-65.8 | F9: -265295.72 | G9: -283216.89 | H9: -286708.42
B10: SALDO ATUAL | C10: =SUM(C7:C9) | D10: =SUM(D7:D9) | E10: =SUM(E7:E9) | F10: =SUM(F7:F9) | G10: =SUM(G7:G9) | H10: =SUM(H7:H9) | I10: =SUM(I7:I9) | J10: =SUM(J7:J9) | ... O10: =SUM(O7:O9)
B12: SALA DE EVENTOS | C12: =C16 | D12: =D16 | E12: =E16 | F12: =F16 | G12: =G16 | H12: =H16 | I12: =I16 | J12: =J16 | ... O12: =O16
B13: SALDO ANTERIOR | C13: 234895.62 | D13: =C16 | E13: =D16 | F13: =E16 | G13: =F16 | H13: =G16 | I13: =H16 | J13: =I16 | K13: =J16 | ... O13: =N16
B14: RECEITA | C14: 2400 | D14: 5245.69 | E14: 3913.8 | F14: 4407.9 | G14: 6337.36 | H14: 5850
B15: DESPESA | C15: 0 | D15: 0 | E15: 0 | F15: 0 | G15: -10451.21 | H15: -10164.8
B16: SALDO ATUAL | C16: =SUM(C13:C15) | D16: =SUM(D13:D15) | E16: =SUM(E13:E15) | F16: =SUM(F13:F15) | G16: =SUM(G13:G15) | H16: =SUM(H13:H15) | I16: =SUM(I13:I15) | J16: =SUM(J13:J15) | ... O16: =SUM(O13:O15)
B18: ESTACIONAMENTO | C18: =C22 | D18: =D22 | E18: =E22 | F18: =F22 | G18: =G22 | H18: =H22 | I18: =I22 | J18: =J22 | ... O18: =O22
B19: SALDO ANTERIOR | C19: 385829.74 | D19: =C22 | E19: =D22 | F19: =E22 | G19: =F22 | H19: =G22 | I19: =H22 | J19: =I22 | K19: =J22 | ... O19: =N22
B20: RECEITA | C20: 17990.62 | D20: 15600 | E20: 15600 | F20: 16822.96 | G20: 15915.18 | H20: 14106.21
B21: DESPESA | C21: -1567.35 | D21: -1144 | E21: -1144 | F21: 0 | G21: -756 | H21: -102374.5
B22: SALDO ATUAL | C22: =SUM(C19:C21) | D22: =SUM(D19:D21) | E22: =SUM(E19:E21) | F22: =SUM(F19:F21) | G22: =SUM(G19:G21) | H22: =SUM(H19:H21) | I22: =SUM(I19:I21) | J22: =SUM(J19:J21) | ... O22: =SUM(O19:O21)
B24: INADIMPLÊNCIA | C24: =C26 | D24: =D26 | E24: =E26 | F24: =F26 | G24: =G26 | H24: =H26 | I24: =I26 | J24: =J26 | ... O24: =O26
B25: SALDO ANTERIOR | C25: 6358.97 | D25: =C26 | E25: =D26 | F25: =E26 | G25: =F26 | H25: =G26 | I25: =H26 | J25: =I26 | K25: =J26 | ... O25: =N26
B26: SALDO ATUAL | C26: 6358.97 | D26: 6358.97 | E26: 6358.97 | F26: 6358.97 | G26: 6358.97 | H26: 6358.97 | I26: 6358.97 | J26: 6358.97 | K26: 6358.97 | L26: 6358.97 | M26: 6358.97 | N26: 6358.97 | O26: 6358.97
B28: FUNDO DE RESERVA | C28: =C30 | D28: =D30 | E28: =E30 | F28: =F30 | G28: =G30 | H28: =H30 | I28: =I30 | J28: =J30 | ... O28: =O30
B29: SALDO ANTERIOR | C29: 4522.65 | D29: =C30 | E29: =D30 | F29: =E30 | G29: =F30 | H29: =G30 | I29: =H30 | J29: =I30 | K29: =J30 | ... O29: =N30
B30: SALDO ATUAL | C30: =C29 | D30: =D29 | E30: =E29 | F30: =F29 | G30: =G29 | H30: =H29 | I30: =I29 | J30: =J29 | ... O30: =O29
B32: BRADESCO | C32: =C34 | D32: =D34 | E32: =E34 | F32: =F34 | G32: =G34 | H32: =H34 | I32: =I34 | J32: =J34 | ... O32: =O34
B33: SALDO ANTERIOR | C33: =114858.61+941415.06 | D33: =C34 | E33: =D34 | F33: =E34 | G33: =F34 | H33: =G34 | I33: =H34 | J33: =I34 | K33: =J34 | ... O33: =N34
B34: SALDO ATUAL | C34: 1116354.1
B36: TOTAL | C36: =C6+C12+C18+C24+C28+C32 | D36: =D6+D12+D18+D24+D28+D32 | E36: =E6+E12+E18+E24+E28+E32 | F36: =F6+F12+F18+F24+F28+F32 | G36: =G6+G12+G18+G24+G28+G32 | H36: =H6+H12+H18+H24+H28+H32 | I36: =I6+I12+I18+I24+I28+I32 | J36: =J6+J12+J18+J24+J28+J32 | ... O36: =O6+O12+O18+O24+O28+O32

Sheet PF 2024
C1: APROVADO
A2: EMPRESA | B2: PREVISÃO ORÇAMENTÁRIA - DIAMOND TOWER | C2: 2024 | D2: MARÇO | E2: ABRIL | F2: MAIO | G2: JUNHO | H2: JULHO | I2: AGOSTO | J2: SETEMBRO | K2: OUTUBRO | L2: NOVEMBRO | M2: DEZEMBRO | N2: JANEIRO | O2: FEVEREIRO | P2: MARÇO | R2: PREVISTO | S2: REALIZADO
B3: CONTRATOS MÃO DE OBRA | C3: =SUM(C4:C16) | D3: =SUM(D4:D16) | E3: =SUM(E4:E16) | F3: =SUM(F4:F16) | G3: =SUM(G4:G16) | H3: =SUM(H4:H16) | I3: =SUM(I4:I16) | J3: =SUM(J4:J16) | ... P3: =SUM(P4:P16) | R3: =SUM(R4:R16) | S3: =SUM(S4:S16)
A4: ONX SERVIÇOS | B4: Monitoramento - 01 Posto 24h - Central de Segurança - ONX | C4: 103500 | D4: =97531.32+5736.92+11470.24 | E4: =87596+5143.71+10134.47 | F4: =87458.17+5143.71+840 | G4: =87596+50+5143.71+10244.47+10535.68 | H4: =87475.58+5143.71+10254.89+2707.48 | I4: =87467.52+5143.71+10262.96+109.41+8.75+65.64+13.12 | J4: =87547.97+5143.71+10182.51+92.29+7.38+55.37+11.07+69.78 | K4: =87537.81+5143.71+10192.67 | L4: =87537.83+165+5141.97+102.66+8.21+61.59+12.31+241.31+198.24+363 | M4: =87606.22+5143.71+20283.86 | N4: =87442.51+5143.71+5636.32 | O4: =94278.05+5556.03+1042.23+11286.57 | R4: =C4*11 | S4: =SUM(F4:P10)
B5: Ronda Vigilante - 01 Posto 24h - ONX
B6: Porteiro 02 postos 8h - (Seg à Dom - das 7h as 22h) - ONX
B7: Expedição 01 posto 8h - (Seg à Sáb - das 08h às 16h20) - ONX
B8: Recepção - 04 postos 8h (das 7h as 22h) - ONX
B9: Limpeza - 03 Postos 44h semanais - ONX
B10: Serviços Gerais – 01 posto 44h semanais - ONX
A11: CAPPELLETTO | B11: Gestor Administrativa 44h - Karoline Aguirres | C11: 16960 | D11: =16000 | E11: =16558.08 | F11: =16000+337.92 | G11: =16950.8 | H11: =16000+345.93 | I11: =16000 | J11: =16720 | K11: =16720 | L11: =16419.04+2111.3 | M11: =16419.04+300.96+38.7+16419.04 | N11: =300.96+300.96 | O11: =17356.85
B12: Gestor Condominial - 01 Posto 44h semanais | R12: =C11*12 | S12: =SUM(D11:P12)
A13: GUARIDA | B13: Auxiliar Administração | C13: 2835 | D13: =24.9+55.8+1139.05+256.82+1430.79 | E13: =58.6+1139.05+78+256.82+37.35+1430.79 | F13: =58.6+1139.05+256.82+22.41+1430.79 | G13: =61.38+1139.05+174+256.82+24.9+1430.79+543.4 | H13: =61.38+1139.05+256.82+1430.79+1.16+47.31 | I13: =1139.05+31.38+1.16+42.33+256.82+1430.79 | J13: =61.38+39.6+1139.05+0.01+256.82+1430.79 | K13: =61.38+1139.05+256.82+1430.79+1.16+24.9 | L13: =61.38+1.16+108.9+1139.05+269.05+1498.9 | M13: =1139.05+1.16+61.38+185+269.05+47.31+1498.9+259.9+259.9 | N13: =1139.05+61.38+1.16+94.05+269.05+1498.9 | R13: =C13*12 | S13: =SUM(D13:P13)
A14: ORGÂNICO | B14: Oficial Manutenção - 01 Posto 44h semanais | C14: 5250 | D14: =3224+291.09+46.65+335.45+727.73+1369.35+90.96+7.27+54.58+10.91+36.38+150.76+36.38+168.8+433.43+601 | E14: =3316+46.65+301.26+79.64+347.79+748.28+1369.35+93.53+7.48+56.12+11.22+37.41+198.26+37.41+168.8+413.86+601 | F14: =3381+2.48+121.69+46.65+3915.96+601+168.8+308.4+98.7+771+96.37+7.71+57.82+11.56+38.55+116.46+38.55+3215 | G14: =45.65+290.07+168.8+452.99+601+112.09+753.14+1369.35+90.64+7.25+54.38+10.87+36.25+27.82+36.25 | H14: =3537+46.65+325.62+77.72+814.06+1369.35+101.75+40.7+40.7+168.8+601 | I14: =3669+48.38+81+350.12+144.38+431.53+875.31+239.68+433.43+201.388+394.3+193.87+600 | J14: =3262+48.38+295.33+194.87+341.81+738.33+36.91+36.91+175.32+452.99+600 | K14: =3882+48.38+366.63+460.42+916.59+45.82+87.59+45.82+78+384+175.32+600 | L14: =3563+102.9+126.72+120+328.53+393.74+821.33+41.06+41.06+2072.63+175.32+403.2+600+48.38+316.8+300+259.9 | M14: =321.19+1195+3088+235.14+82.24+302.81+102.9+48.38+48.38+681+1508.26+46.71+542.3+1492.12+371.19+941.24+47.06+47.06+120+67.2+175.32+76.8+5203.24+300+211.2 | N14: =3046+681+48.38+48.38+585.65+423.52+1052.35+52.61+304.55+52.61+175.32+192+384+900+200+1212+874+778 | O14: =681+48.38+48.38+554.87+201.6+649.48+1387.2+69.36+173.4+13.87+104.04+20.8+43.31+195.61+69.36+175.32+403.2 | R14: =C14*11 | S14: =SUM(D14:P14)
A15: ORGÂNICO | B15: Remuneração Subsíndico | C15: 7500 | D15: =6093.62+753.14 | E15: =6093.62+753.14 | F15: =6093.62+361.41+753.14 | G15: =6093.62+333.92+725.18 | H15: =6093.62+388.65+753.14 | I15: =6093.62+753.14+1369.35 | J15: =6093.62+753.14+1369.35 | K15: =6093.62+753.14+1369.35 | L15: =6093.62+753.14+1369.75 | M15: =6093.62+753.14+1369.35 | N15: =6093.62+790.56+1437.4+359.44 | O15: =7206.2+753.14+1369.35 | R15: =C15*12 | S15: =SUM(D15:P15)
A16: AUDI PASTAS | B16: Auditoria Externa | C16: 1330 | D16: =26.6+1303.4 | E16: =26.6+1303.4 | F16: =26.6+1303.4 | G16: =26.6+1303.4 | H16: =26.6+1303.4 | I16: =26.6+1303.4 | J16: =26.6+1303.4 | K16: =26.6+1303.4 | ... N16: =26.6+1303.4 | O16: =26.6 | R16: =C16*12 | S16: =SUM(D16:P16)
B18: MANUTENÇÕES/LOCAÇÕES - CONTRATOS | C18: =SUM(C19:C24) | D18: =SUM(D19:D23) | E18: =SUM(E19:E23) | F18: =SUM(F19:F23) | G18: =SUM(G19:G23) | H18: =SUM(H19:H23) | I18: =SUM(I19:I23) | J18: =SUM(J19:J23) | K18: =SUM(K19:K23) | ... P18: =SUM(P19:P23) | R18: =SUM(R19:R24) | S18: =SUM(S19:S24)
A19: FG PISCINAS | B19: Limpeza Espelho D'água, Química e AFT com Material | C19: 850 | D19: =9+19.8+771.85 | E19: =8.35+19.8+771.85 | F19: =8.35+771.85+19.8+8.51 | G19: =774.77 | H19: =7.63+17.6 | I19: =774.91+774.92 | J19: =20.18+17.6+774.89+7.62 | K19: =7.51+17.6+782.4 | L19: =17.6+898.81 | M19: =6.34+14.85+898.82 | N19: =6.33+27.22+78.65+898.97 | O19: =14.85 | R19: =C19*12 | S19: =SUM(D19:P19)
A20: BDS AR | B20: Manutenção ar condicionado / exaustão áreas comuns | C20: 0 | D20: =3309.98+152.7 | E20: =3294.05+168.63 | F20: =1644.77+86.57+931 | G20: =19+2380 | M20: 1274 | N20: =26 | R20: =C20*12 | S20: =SUM(D20:P20)
A21: ATLAS | B21: Manutenção Preventiva Elevadores (7) - Com Peças - Atlas | C21: 9000 | D21: =2.02+461.19+38.47+694.2 | E21: =461.19 | G21: =461.19+694.49+694.47+694.47+694.47+8333.7+2777.9+8333.7 | H21: =461.19+2777.9 | I21: =461.19 | J21: =2777.9+461.18+2777.9 | K21: =1500+461.18+2777.9 | L21: =461.18+2777.9 | M21: =461.18+8333.7+8333.55+8333.53+8333.53+8333.53+2777.9+6034 | N21: =2777.9+8333.53 | O21: =461.18 | R21: =C21*12 | S21: =SUM(D21:P21)
A22: ALTITUDE | B22: Limpeza da Fachada | C22: 8350 | D22: =240+1509.65+35.15 | G22: =196 | M22: =9000 | N22: =9000+9000 | O22: =9000 | R22: =C22*12 | S22: =SUM(D22:P22)
A23: STEMAC | B23: Manutenção preventiva motor gerador | C23: 1449.41 | D23: =1096.19+69.07+151.95+1096.19 | E23: =69.07+151.95 | F23: =1096.19+69.07+151.96 | G23: =1096.19+69.07+151.96 | H23: =1096.19+69.07+151.95+1096.19 | I23: =69.07+151.96 | J23: =1096.19+69.07+151.96 | K23: =1096.19+69.07+151.96+1096.19 | L23: =69.07+151.96 | M23: =1096.19+140.16+69.07 | N23: =1096.19+69.07+151.96 | O23: =1167.75+73.58+161.88 | R23: =C23*12 | S23: =SUM(D23:P23)
A24: BELLINI | B24: Consultoria jurídica | C24: 2824 | D24: =2763.28+60.72 | E24: =2764.13+59.87 | F24: =2758.2 | G24: =2756.22+67.78 | H24: 2767.52 | I24: =2757.07+66.93 | J24: =2753.12+70.88 | K24: =2753.12+70.88 | L24: =2752.84+71.16 | M24: =2752.84+71.16 | N24: =2752.55+71.45 | O24: =2959.19+76.81 | R24: =C24*12 | S24: =SUM(D24:P24)
B26: MANUTENÇÕES - SEM CONTRATO | C26: =SUM(C27:C34) | D26: =SUM(D27:D34) | E26: =SUM(E27:E34) | F26: =SUM(F27:F34) | G26: =SUM(G27:G34) | H26: =SUM(H27:H34) | I26: =SUM(I27:I34) | J26: =SUM(J27:J34) | ... P26: =SUM(P27:P34) | R26: =SUM(R27:R34) | S26: =SUM(S27:S34)
A27: MULTIPLAN | B27: Lixo/Entulho/Manutenção Externa - Despesa Compartilhada | C27: 3000 | D27: =3031.82 | E27: 1776.8 | F27: =1705.54+3074.35 | H27: =1852.91 | I27: =2574.93 | J27: =1808.99+2232.07 | K27: =2081.49 | L27: =1854.73 | M27: =3269.33 | R27: =C27*12 | S27: =SUM(D27:P27)
A28: DEMANDA | B28: Manutenção Bombas de Recalque | C28: 525 | I28: =140 | M28: =664.49 | N28: =664.49 | O28: =3556.3 | R28: =C28*12 | S28: =SUM(D28:P28)
B29: Manutenção Interfones | C29: 500 | E29: =150 | J29: =580+280 | K29: =9.8+270.2 | L29: =9.8 | O29: =270.2 | R29: =C29*12 | S29: =SUM(D29:P29)
B30: Manutenção Predial | C30: 4000 | D30: =286+195+425.27 | E30: =165+34.93+129.8+173.94+85+1800+590 | F30: =612 | H30: =3153.2+2376.25+3148.95+583.19+1478 | I30: =557.9+373.84+285+1456.95+3590 | J30: =370.5+343.8+16.2 | K30: =92.7+89.12+2772 | L30: =124.75+1500+1700+790 | N30: =1570+12369.32 | O30: =1361.99 | R30: =C30*12 | S30: =SUM(D30:P30)
B31: Manutenção Preventiva Sistema de Incêndio | C31: 315 | I31: =48.73+2375.88 | L31: =1250 | R31: =C31*12 | S31: =SUM(D31:P31)
B32: Obrigações Legais (AFT, certificado de qualidade do ar de ambiente climatizado, certificado digital, inspeção da esccada pressurizada, laudo de potabilidade, teste mangueiras, recarga extintores, SPDA, subestação de energia) | C32: 3200 | D32: =18+2.48+121.69 | E32: =2.48+121.69 | F32: =1159.4 | G32: =121.69+1159.4+166.4 | H32: =2.48+480+121.69+352.36 | I32: =121.69+19.5+2.48+480+4894.85+2082.5 | J32: =312.1+2.48+42.5+10.84+121.69+480+4894.85 | K32: =1166.2+2.48+122.52+3795 | L32: =1540.16+246+2.5+23.8+4855+1159.4+261.27 | M32: =1159.4+59.84+2.1+179.8+6497.55+818.21+1020+645+1515+1684.13 | N32: =31.79+252.45+2.1+102.9+295.1+4157.23+11800 | O32: =4158.96+3936.98+102.9+2.1+172.77+816.42+6483.38+1150 | R32: =C32*12 | S32: =SUM(D32:P32)
B33: Controle Pragas e Limpeza Caixa D'água (2x ano) | C33: 525 | R33: =C33*12 | S33: =SUM(D33:P33)
B34: Paisagismo interno | C34: 105 | E34: =833.34 | F34: =833.33 | G34: =833.33 | R34: =C34*12 | S34: =SUM(D34:P34)
B36: MATERIAIS E EQUIPAMENTOS | C36: =SUM(C37:C48) | D36: =SUM(D37:D48) | E36: =SUM(E37:E48) | F36: =SUM(F37:F48) | G36: =SUM(G37:G48) | H36: =SUM(H37:H48) | I36: =SUM(I37:I48) | J36: =SUM(J37:J48) | ... P36: =SUM(P37:P48) | R36: =SUM(R37:R48) | S36: =SUM(S37:S48)
B37: Chaveiro | C37: 20 | E37: =160 | H37: =250 | L37: =260 | N37: =340 | R37: =C37*12 | S37: =SUM(D37:P37)
B38: Lâmpadas | C38: 500 | D38: =319 | E38: =267+98.9 | H38: =91.6 | I38: =774 | J38: =1229.87 | K38: =774 | R38: =C38*12 | S38: =SUM(D38:P38)
B39: Materiais/Serviços Obras Diversas (Alvenaria, Serralheria, Funilaria, Outros) | C39: 1500 | D39: =88.15 | E39: =1000.01 | G39: =90+302+337.6+380 | H39: =99.6+394.57+306+291.35+557.9+692.6+369 | I39: =542+181.45 | K39: =91.01+735 | L39: =15+240.91+88.7+49.5+527.95+280+298+200+65.6+521.7 | M39: =3040.45 | N39: =250+150+1150+298+140 | O39: =545+151.6+257.35+110.05+485.95 | R39: =C39*12 | S39: =SUM(D39:P39)
B40: Material de Ferragem (Elétrica, Hidráulica e Ferramentas) | C40: 2000 | D40: =56.91+28.98+43+180.9+48.9+291.79+349.17+291.79 | E40: =395.3+1625.85 | F40: =94+211.6+296.35 | G40: =284.7+385+60.8+190.65+35.96+13.3+315+90+978.87 | H40: =1229.87+219.99+372.95+400.55 | I40: =119.38+1229.87+49.98+138.7+133.95+126.65+400.55 | J40: =65.1+72.75+117.5+1065.9+32.3+99.5+298 | K40: =86.13+478.82+657.05+298+156.5 | L40: =284.12+521.71+388.44+430+325.6+53.05+190+18.5+741.05 | M40: =459.9+364.8+66.65+340.2+814.34+118.9+843.45+298 | N40: =946.37+147.35+67.5+74.8+110.02+79.8+447 | O40: =397.72+845+727.85 | R40: =C40*12 | S40: =SUM(D40:P40)
B41: Material Expediente Interno | C41: 500 | D41: =65.83 | E41: =144.59 | F41: =152.85+96.94 | G41: =34.18 | H41: =132.2+90.72+17.09+684.82 | I41: =179.51+138+679.34+112.5 | J41: =155.5+56.97+934.16+134.62 | K41: =236.57 | L41: =528.36 | M41: =913.61 | N41: =171.83 | O41: =903.37 | R41: =C41*12 | S41: =SUM(D41:P41)
B42: Material Limpeza/Consumíveis | C42: 2000 | D42: =115.3+446.9 | E42: =699.13+54.38+244+600.78 | F42: =805.05+348.43+970.5 | G42: =458.35+348.43 | H42: =679.93+348.43 | I42: =713.37+698.4+348.43 | J42: =258.96+655.92 | K42: =763.16+297.1 | L42: =480.15+168.48+1061.64 | M42: =662.98+1004.24 | N42: =449.83+414.81+759.8 | O42: =273.95 | R42: =C42*12 | S42: =SUM(D42:P42)
A43: ATLAS | B43: Peças elevador | C43: 700 | E43: =459.65+447.15+694.2 | F43: =694.19 | K43: =461.18 | M43: =322.1+542.1+79.18+225.91+79.18+322.1+322.1+542.1 | N43: =333.92+38.47+332.1+542.1 | R43: =C43*12 | S43: =SUM(D43:P43)
A44: DEMANDA | B44: Móveis e Utensílios | C44: 600 | E44: =4506.04+218.33+79.9 | F44: =91.96 | H44: =421.32 | K44: =558.36 | L44: =255+760+714.8 | M44: =1143.46+290 | N44: =280 | O44: =433.49 | R44: =C44*12 | S44: =SUM(D44:P44) | U44: despesa de cartão | V44: 903 pila
B45: Peças Ar Condicionado/Exaustores | C45: 525 | D45: =1200 | R45: =C45*12 | S45: =SUM(D45:P45)
B46: Peças de reposição para extintores e hidrantes e recargas eventuais | C46: 150 | I46: =530 | J46: =140 | R46: =C46*12 | S46: =SUM(D46:P46)
B47: Peças para Grupo Gerador, limpeza semestral filtro e óleo e óleo diesel | C47: 500 | F47: =308.19+2359.32+566 | G47: =283 | K47: =325.44+886.72 | L47: =140.16+318.45+867.63 | M47: =319.99+318.54+867.9 | N47: =140.19 | R47: =C47*12 | S47: =SUM(D47:P47)
B48: Peças para manutenção das catracas | C48: 350 | I48: =269.16 | M48: =3219.78 | N48: =2466.72 | O48: =1284.74 | R48: =C48*12 | S48: =SUM(D48:P48)
B50: DESPESAS ADMINISTRATIVAS | C50: =SUM(C51:C56) | D50: =SUM(D51:D55) | E50: =SUM(E51:E55) | F50: =SUM(F51:F55) | G50: =SUM(G51:G55) | H50: =SUM(H51:H55) | I50: =SUM(I51:I55) | J50: =SUM(J51:J55) | K50: =SUM(K51:K55) | ... P50: =SUM(P51:P55) | R50: =SUM(R51:R56) | S50: =SUM(S51:S56)
B51: Telefonia/Internet- apenas telefone, internet comodato | C51: 250 | D51: =50.63+61.51 | E51: =49.49+99.98 | F51: =98.49+99.98 | G51: =39.9+99.98 | H51: =39.9+99.98 | I51: =39.9+99.98 | J51: =39.9+99.98 | K51: =102.02+40.7 | L51: =101.12+39.9 | M51: =101.12 | N51: =40.8+101.12+39.9 | O51: =101.12 | R51: =C51*12 | S51: =SUM(D51:P51)
B52: Correio/Remessa Correspondências/Motoboy/Diversas | C52: 150 | D52: =29.89+17.9+25.16+18.5 | E52: =44.51 | I52: =44.51 | J52: =36.98 | K52: =190 | M52: =2.02+117.65+9.41+70.59+14.11+149.83+27.82+202.46 | R52: =C52*12 | S52: =SUM(D52:P52)
B53: Impostos - DIRF/DARF/ISSQN/PIS/COFINS | C53: 170 | D53: =25.44+24.75 | E53: =91.26+74.5 | F53: =461.19 | G53: =2.48+597.23 | H53: =81.4 | K53: =3090.49+114.57+9.16+68.74+13.74+134.01 | L53: =170.84 | N53: =131.54+10.52+78.92+15.78 | O53: =243.21 | R53: =C53*12 | S53: =SUM(D53:P53)
B54: Taxa Desepesas com Assembleia | C54: 150 | R54: =C54*12 | S54: =SUM(D54:P54)
B55: Custas Judiciais | C55: 200 | D55: =412.2 | R55: =C55*12 | S55: =SUM(D55:P55)
A56: GOOGLE | B56: Hospedagem / Domínio Corporativo | C56: 200 | D56: =162 | E56: =188.12 | F56: =252 | H56: =302 | I56: =252 | K56: =252 | L56: =252 | R56: =C56*12 | S56: =SUM(D56:P56)
B58: COTA | C58: =C3+C18+C26+C36+C50 | D58: =SUM(D3,D18,D26,D36,D50) | E58: =SUM(E3,E18,E26,E36,E50) | F58: =SUM(F3,F18,F26,F36,F50) | G58: =SUM(G3,G18,G26,G36,G50) | H58: =SUM(H3,H18,H26,H36,H50) | I58: =SUM(I3,I18,I26,I36,I50) | J58: =SUM(J3,J18,J26,J36,J50) | K58: =SUM(K3,K18,K26,K36,K50) | ... P58: =SUM(P3,P18,P26,P36,P50) | R58: =C58*12 | S58: =S3+S18+S26+S36+S50
B60: DESPESAS VARIÁVEIS | C60: R$ - | D60: =SUM(D61:D63) | E60: =SUM(E61:E63) | F60: =SUM(F61:F63) | G60: =SUM(G61:G63) | H60: =SUM(H61:H63) | I60: =SUM(I61:I63) | J60: =SUM(J61:J63) | K60: =SUM(K61:K63) | ... P60: =SUM(P61:P63) | R60: =SUM(R61:R63) | S60: =SUM(S61:S63)
B61: Água e Esgoto - Área Comum | C61: - | E61: =11626.27+9552.81 | F61: =9552.81 | G61: =9552.81 | H61: =9552.81 | I61: =9552.81 | J61: =9552.81 | K61: =9552.81 | L61: =9552.81 | M61: =9552.81 | ... O61: =9552.81 | S61: =SUM(D61:P61)
B62: Energia Elétrica - Área Comum | C62: - | E62: =19020.77+22207.26 | F62: =19922.55 | H62: =17480.64+18304.5 | I62: =19879.76 | J62: =19825.49 | K62: =19684.02 | L62: =22611.32 | M62: =19895.15 | N62: =20245.43 | S62: =SUM(D62:P62)
B63: Seguro fogo | C63: - | H63: 5192.48 | J63: =5192.37 | K63: =5192.37 | L63: =5192.37 | M63: =5192.37 | N63: =5192.3 | S63: =SUM(D63:P63)
B65: OUTRAS DESPESAS | C65: R$ - | D65: =SUM(D66:D70) | E65: =SUM(E66:E70) | F65: =SUM(F66:F70) | G65: =SUM(G66:G70) | H65: =SUM(H66:H70) | I65: =SUM(I66:I70) | J65: =SUM(J66:J70) | K65: =SUM(K66:K70) | ... P65: =SUM(P66:P70) | R65: =SUM(R66:R69) | S65: =SUM(S66:S70)
B66: Despesas Não Orçadas | C66: - | D66: =3079.5+868.15 | E66: =720.8+160+8.94+22.56 | F66: =12800+5404 | G66: =12800 | H66: =12800+5000+25770.36+230.5 | I66: =36507.93+36507.93 | J66: =36507.93 | K66: =5356.85+983.65+529.26 | L66: =5356.85+983.65+666.44 | M66: =11619.03+11619.03+11619.03 | N66: =11169.03+36507.85 | S66: =SUM(D66:P66)
B67: Despesas reembolsáveis | D67: =784 | E67: =453.01+240.41+2116.39+16+1416.83 | F67: =1416.83+453.01 | G67: =1416.83+453.01 | H67: =28.92+9.25+453.01+1416.83+495.4 | I67: =9.25+28.92+10.11+134.45+1416.83+453.01 | J67: =2.74+28.92+9.25+276.95 | K67: =453.01+1416.83+9.25+28.92+1350 | M67: =260.15+4920+864+2875 | N67: =5.31 | R67: =C67*12 | S67: =SUM(D67:P67)
B68: Honorários advocatícios | D68: =978.5+978.5+1957+21.5+21.5+43 | E68: =978.8+978.8+1957.6+489.4+489.4+978.8+21.2+83.7+21.2+42.4+10.6+10.6+50.4+21.2 | F68: =1953.4+976.7+488.35+488.35+976.7+976.7+976.7+9.25+28.92+5.74+65.8+46.6+23.3+11.65+11.65+23.3+23.3+23.3+43.19 | G68: =976+976+1952+488+488+976+976+28.92+9.25+24+24+48+12+12+24+24 | H68: =1960+490+980+980+10+40+56.48+10+20+20+490 | I68: =488.15+1952.6+976.3+976.3+976.3+976.3+488.15+47.4+23.7+23.7+23.7+23.7+11.85+11.85 | J68: =1949.8+974.9+974.9+974.9+487.45+487.45+50.2+25.1+25.1+25.1+12.55+12.55 | K68: =974.9+974.9+487.45+487.45+25.1+25.1+12.55+12.55 | L68: =974.8+974.8+487.4+487.4+974.8+25.2+25.2+12.6+12.6+25.2 | M68: =487.4+487.4+974.8+974.8+974.8+12.6+12.6+25.2+25.2+25.2 | N68: =487.35+487.35+974.7+12.65+12.65+25.3 | O68: =974.7+25.3+2436.25+2436.25 | R68: =C68*12 | S68: =SUM(D68:P68)
B69: Ampliação do CFTV | D69: =180+12924.2 | E69: =180+32.4+13.95 | G69: =12376.51 | H69: =12485.76 | R69: =C69*12 | S69: =SUM(D69:P69)
B70: Transferências Entre Contas | C70: -
B72: TOTAL DESPESAS CONTA PRINCIPAL | C72: =C58 | D72: =D65+D60+D58 | E72: =E65+E60+E58 | F72: =F65+F60+F58 | G72: =G65+G60+G58 | H72: =H65+H60+H58 | I72: =I65+I60+I58 | J72: =J65+J60+J58 | K72: =K65+K60+K58 | ... M72: =M65+M60+M58 | N72: =N58+N60+N65 | O72: =O58+O60+O65 | P72: =P65+P60+P58 | R72: =R58+R60+R65 | S72: =S58+S60+S65 | U72: =(S58+S65)-S67
U73: =U72-R72

Sheet RS 2024
C2: RESUMO DE SALDOS
C3: 2024 | O3: 2025
B4: CONTA | C4: MARÇO | D4: ABRIL | E4: MAIO | F4: JUNHO | G4: JULHO | H4: AGOSTO | I4: SETEMBRO | J4: OUTUBRO | K4: NOVEMBRO | L4: DEZEMBRO | M4: JANEIRO | N4: FEVEREIRO | O4: MARÇO
B6: PRINCIPAL | C6: =C10 | D6: =D10 | E6: =E10 | F6: =F10 | G6: =G10 | H6: =H10 | I6: =I10 | J6: =J10 | ... O6: =O10
B7: SALDO ANTERIOR | C7: 16871.3 | D7: =C10 | E7: =D10 | F7: =E10 | G7: =F10 | H7: =G10 | I7: =H10 | J7: =I10 | K7: =J10 | ... O7: =N10
B8: RECEITA | C8: 204236.66 | D8: 191434.5 | E8: 243335.54 | F8: 236208.99 | G8: 235527.16 | H8: 236642.1 | I8: 232346.51 | J8: 219206.53 | K8: 212433.84 | L8: 211554.13 | M8: 214325.07 | N8: 215181.27
B9: DESPESA | C9: -191575.88 | D9: -238300.53 | E9: -215132.72 | F9: -228131.61 | G9: -284997.84 | H9: -282574.06 | I9: -243571.57 | J9: -218526.74 | K9: -216941.31 | L9: -359797.57 | M9: -283655.73 | N9: -266100.77
B10: SALDO ATUAL | C10: =SUM(C7:C9) | D10: =SUM(D7:D9) | E10: =SUM(E7:E9) | F10: =SUM(F7:F9) | G10: =SUM(G7:G9) | H10: =SUM(H7:H9) | I10: =SUM(I7:I9) | J10: =SUM(J7:J9) | ... O10: =SUM(O7:O9)
B12: SALA DE EVENTOS | C12: =C16 | D12: =D16 | E12: =E16 | F12: =F16 | G12: =G16 | H12: =H16 | I12: =I16 | J12: =J16 | ... O12: =O16
B13: SALDO ANTERIOR | C13: 174810.85 | D13: =C16 | E13: =D16 | F13: =E16 | G13: =F16 | H13: =G16 | I13: =H16 | J13: =I16 | K13: =J16 | ... O13: =N16
B14: RECEITA | C14: 7100 | D14: 4200 | E14: 9975 | F14: 8800 | G14: 1309 | H14: 6314.74 | I14: 5000 | J14: 9533.2 | K14: 5450 | L14: 5550 | M14: 5575 | N14: 3822.91
B15: DESPESA | C15: 0 | D15: -1900 | E15: -100 | F15: 0 | G15: 0 | H15: 0 | I15: 0 | J15: 0 | K15: -1516 | L15: 0 | M15: -9029.08 | N15: 0 | O15: 0
B16: SALDO ATUAL | C16: =SUM(C13:C15) | D16: =SUM(D13:D15) | E16: =SUM(E13:E15) | F16: =SUM(F13:F15) | G16: =SUM(G13:G15) | H16: =SUM(H13:H15) | I16: =SUM(I13:I15) | J16: =SUM(J13:J15) | ... O16: =SUM(O13:O15)
B18: ESTACIONAMENTO | C18: =C22 | D18: =D22 | E18: =E22 | F18: =F22 | G18: =G22 | H18: =H22 | I18: =I22 | J18: =J22 | ... O18: =O22
B19: SALDO ANTERIOR | C19: 193938.04 | D19: =C22 | E19: =D22 | F19: =E22 | G19: =F22 | H19: =G22 | I19: =H22 | J19: =I22 | K19: =J22 | ... O19: =N22
B20: RECEITA | C20: 13172.23 | D20: 12967.84 | E20: 12975.84 | F20: 18354.5 | G20: 17935.45 | H20: 18646.37 | I20: 18614.09 | J20: 16513.4 | K20: 17433.49 | L20: 17120.99 | M20: 17546.84 | N20: 18055.41
B21: DESPESA | C21: 0 | D21: 0 | E21: 0 | F21: 0 | G21: 0 | H21: 0 | I21: 0 | J21: -4900 | K21: -119.6 | L21: -492.4 | M21: 0 | N21: -1932.75 | O21: 0
B22: SALDO ATUAL | C22: =SUM(C19:C21) | D22: =SUM(D19:D21) | E22: =SUM(E19:E21) | F22: =SUM(F19:F21) | G22: =SUM(G19:G21) | H22: =SUM(H19:H21) | I22: =SUM(I19:I21) | J22: =SUM(J19:J21) | ... O22: =SUM(O19:O21)
B24: INADIMPLÊNCIA | C24: =C26 | D24: =D26 | E24: =E26 | F24: =F26 | G24: =G26 | H24: =H26 | I24: =I26 | J24: =J26 | ... O24: =O26
B25: SALDO ANTERIOR | C25: 6358.97 | D25: =C26 | E25: =D26 | F25: =E26 | G25: =F26 | H25: =G26 | I25: =H26 | J25: =I26 | K25: =J26 | ... O25: =N26
B26: SALDO ATUAL | C26: 6358.97 | D26: 6358.97 | E26: 6358.97 | F26: 6358.97 | G26: 6358.97 | H26: 6358.97 | I26: 6358.97 | J26: 6358.97 | K26: 6358.97 | L26: 6358.97 | M26: 6358.97 | N26: 6358.97 | O26: 6358.97
B28: FUNDO DE RESERVA | C28: =C30 | D28: =D30 | E28: =E30 | F28: =F30 | G28: =G30 | H28: =H30 | I28: =I30 | J28: =J30 | ... O28: =O30
B29: SALDO ANTERIOR | C29: 4522.65 | D29: =C30 | E29: =D30 | F29: =E30 | G29: =F30 | H29: =G30 | I29: =H30 | J29: =I30 | K29: =J30 | ... O29: =N30
B30: SALDO ATUAL | C30: 4522.65 | D30: 4522.65 | E30: 4522.65 | F30: 4522.65 | G30: 4522.65 | H30: 4522.65 | I30: 4522.65 | J30: 4522.65 | K30: 4522.65 | L30: 4522.65 | M30: 4522.65 | N30: 4522.65 | O30: 4522.65
B32: BRADESCO | C32: =C34 | D32: =D34 | E32: =E34 | F32: =F34 | G32: =G34 | H32: =H34 | I32: =I34 | J32: =J34 | ... O32: =O34
B33: SALDO ANTERIOR | C33: =114858.61+941415.06 | D33: =C34 | E33: =D34 | F33: =E34 | G33: =F34 | H33: =G34 | I33: =H34 | J33: =I34 | K33: =J34 | ... O33: =N34
B34: SALDO ATUAL | C34: 1116354.1
B36: TOTAL | C36: =C6+C12+C18+C24+C28+C32 | D36: =D6+D12+D18+D24+D28+D32 | E36: =E6+E12+E18+E24+E28+E32 | F36: =F6+F12+F18+F24+F28+F32 | G36: =G6+G12+G18+G24+G28+G32 | H36: =H6+H12+H18+H24+H28+H32 | I36: =I6+I12+I18+I24+I28+I32 | J36: =J6+J12+J18+J24+J28+J32 | ... O36: =O6+O12+O18+O24+O28+O32

Sheet PO 2024
C1: APROVADO | D1: SUGESTÃO
A2: EMPRESA | B2: PREVISÃO ORÇAMENTÁRIA - DIAMOND TOWER | C2: 2023 | D2: 2024 | E2: MARÇO | F2: ABRIL | G2: MAIO | H2: JUNHO | I2: JULHO | J2: AGOSTO | K2: SETEMBRO | L2: OUTUBRO | M2: NOVEMBRO | N2: DEZEMBRO | O2: JANEIRO | P2: FEVEREIRO | Q2: MARÇO | S2: PREVISTO | T2: REALIZADO
A3: JAN-MAI | B3: CONTRATOS MÃO DE OBRA | C3: 133630.24 | D3: =SUM(D4:D17) | E3: =SUM(E4:E16) | F3: =SUM(F4:F16) | G3: =SUM(G4:G16) | H3: =SUM(H4:H16) | I3: =SUM(I4:I16) | J3: =SUM(J4:J16) | K3: =SUM(K4:K16) | L3: =SUM(L4:L16) | ... Q3: =SUM(Q4:Q16) | S3: =SUM(S4:S16) | T3: =SUM(T4:T16)
A4: ONX SERVIÇOS | B4: Monitoramento - 01 Posto 24h - Central de Segurança - ONX | C4: 112542 | D4: 110000 | S4: =C4*11 | T4: =SUM(G4:Q10)
B5: Ronda Vigilante - 01 Posto 24h - ONX
B6: Porteiro 02 postos 8h - (Seg à Dom - das 7h as 22h) - ONX
B7: Expedição 01 posto 8h - (Seg à Sáb - das 08h às 16h20) - ONX
B8: Recepção - 04 postos 8h (das 7h as 22h) - ONX
B9: Limpeza - 03 Postos 44h semanais - ONX
B10: Serviços Gerais – 01 posto 44h semanais - ONX
A11: CAPPELLETTO | B11: Assistente Condominial 44h - Karoline Aguirres | C11: 16000 | D11: =16000*1.06
B12: Gestor Condominial - 01 Posto 44h semanais | S12: =C12*12 | T12: =SUM(E12:Q12)
A13: GUARIDA | B13: Auxiliar Administração | C13: 2700 | D13: =C13*1.05 | S13: =C13*12 | T13: =SUM(E13:Q13)
A14: ORGÂNICO | B14: Oficial Manutenção - 01 Posto 44h semanais | C14: 5000 | D14: =C14*1.05 | S14: =C14*11 | T14: =SUM(E14:Q14)
A15: ORGÂNICO | B15: Remuneração Subsíndico | C15: 5222.24 | D15: 7500 | S15: =C15*12 | T15: =SUM(E15:Q15)
A16: AUDI PASTAS | B16: Auditoria Externa | C16: 1166 | D16: 1330 | S16: =C16*12 | T16: =SUM(E16:Q16)
B18: MANUTENÇÕES/LOCAÇÕES - CONTRATOS | C18: 27460.78 | D18: =SUM(D19:D26) | E18: =SUM(E19:E25) | F18: =SUM(F19:F25) | G18: =SUM(G19:G25) | H18: =SUM(H19:H25) | I18: =SUM(I19:I25) | J18: =SUM(J19:J25) | K18: =SUM(K19:K25) | L18: =SUM(L19:L25) | ... Q18: =SUM(Q19:Q25) | S18: =SUM(S19:S26) | T18: =SUM(T19:T26)
A19: FG PISCINAS | B19: Limpeza Espelho D'água, Química e AFT com Material | C19: 850 | D19: 850 | S19: =C19*12 | T19: =SUM(E19:Q19)
A20: SYSCOM | B20: Locação Impressora | C20: 223.82 | D20: 0 | S20: =C20*12 | T20: =SUM(E20:Q20)
A21: BDS AR | B21: Manutenção ar condicionado / exaustão áreas comuns | C21: 3339.14 | D21: =C21*1.05 | S21: =C21*12 | T21: =SUM(E21:Q21)
A22: SYSCOM | B22: Manutenção CFTV/Controle de Acesso/Central Alarme | C22: 3536.46 | D22: 0 | S22: =C22*12 | T22: =SUM(E22:Q22)
A23: ATLAS | B23: Manutenção Preventiva Elevadores (7) - Com Peças - Atlas | C23: 8680.97 | D23: 9223.79 | S23: =C23*12 | T23: =SUM(E23:Q23)
A24: ALTITUDE | B24: Limpeza da Fachada | C24: 7500 | D24: 8350 | S24: =C24*12 | T24: =SUM(E24:Q24)
A25: STEMAC | B25: Manutenção preventiva motor gerador | C25: 1380.39 | D25: =C25*1.05 | S25: =C25*12 | T25: =SUM(E25:Q25)
A26: BELLINI | B26: Consultoria jurídica | C26: 1950 | D26: =1412*2 | S26: =C26*12 | T26: =SUM(E26:Q26)
B28: MANUTENÇÕES - SEM CONTRATO | C28: 10450 | D28: =SUM(D29:D36) | E28: =SUM(E29:E36) | F28: =SUM(F29:F36) | G28: =SUM(G29:G36) | H28: =SUM(H29:H36) | I28: =SUM(I29:I36) | J28: =SUM(J29:J36) | K28: =SUM(K29:K36) | ... Q28: =SUM(Q29:Q36) | S28: =SUM(S29:S36) | T28: =SUM(T29:T36)
A29: MULTIPLAN | B29: Lixo/Entulho/Manutenção Externa - Despesa Compartilhada | C29: 3000 | D29: 3000 | S29: =C29*12 | T29: =SUM(E29:Q29)
A30: DEMANDA | B30: Manutenção Bombas de Recalque | C30: 500 | D30: =C30*1.05 | S30: =C30*12 | T30: =SUM(E30:Q30)
B31: Manutenção Interfones | C31: 50 | D31: 500 | S31: =C31*12 | T31: =SUM(E31:Q31)
B32: Manutenção Predial | C32: 3000 | D32: 3000 | S32: =C32*12 | T32: =SUM(E32:Q32)
B33: Manutenção Preventiva Sistema de Incêndio | C33: 300 | D33: =C33*1.05 | S33: =C33*12 | T33: =SUM(E33:Q33)
B34: Obrigações Legais (AFT, certificado de qualidade do ar de ambiente climatizado, certificado digital, inspeção da esccada pressurizada, laudo de potabilidade, teste mangueiras, recarga extintores, SPDA, subestação de energia) | C34: 3000 | D34: 3000 | S34: =C34*12 | T34: =SUM(E34:Q34)
B35: Controle Pragas e Limpeza Caixa D'água (2x ano) | C35: 500 | D35: =C35*1.05 | S35: =C35*12 | T35: =SUM(E35:Q35)
B36: Paisagismo interno | C36: 100 | D36: =C36*1.05 | S36: =C36*12 | T36: =SUM(E36:Q36)
B38: MATERIAIS E EQUIPAMENTOS | C38: 6320 | D38: =SUM(D39:D51) | E38: =SUM(E39:E51) | F38: =SUM(F39:F51) | G38: =SUM(G39:G51) | H38: =SUM(H39:H51) | I38: =SUM(I39:I51) | J38: =SUM(J39:J51) | K38: =SUM(K39:K51) | ... Q38: =SUM(Q39:Q51) | S38: =SUM(S39:S51) | T38: =SUM(T39:T51)
A39: DEMANDA | B39: Cartões para controle de acesso | C39: 200 | D39: 0 | S39: =C39*12 | T39: =SUM(E39:Q39)
B40: Chaveiro | C40: 20 | D40: 20 | S40: =C40*12 | T40: =SUM(E40:Q40)
B41: Lâmpadas | C41: 500 | D41: =C41*1.05 | S41: =C41*12 | T41: =SUM(E41:Q41)
B42: Materiais/Serviços Obras Diversas (Alvenaria, Serralheria, Funilaria, Outros) | C42: 600 | D42: 800 | S42: =C42*12 | T42: =SUM(E42:Q42)
B43: Material de Ferragem (Elétrica, Hidráulica e Ferramentas) | C43: 600 | D43: 1000 | S43: =C43*12 | T43: =SUM(E43:Q43)
B44: Material Expediente Interno | C44: 300 | D44: 500 | S44: =C44*12 | T44: =SUM(E44:Q44)
B45: Material Limpeza/Consumíveis | C45: 2000 | D45: 2000 | S45: =C45*12 | T45: =SUM(E45:Q45)
A46: ATLAS | B46: Peças elevador | C46: 500 | D46: 700 | S46: =C46*12 | T46: =SUM(E46:Q46)
A47: DEMANDA | B47: Móveis e Utensílios | C47: 500 | D47: 700 | S47: =C47*12 | T47: =SUM(E47:Q47)
B48: Peças Ar Condicionado/Exaustores | C48: 500 | D48: =C48*1.05 | S48: =C48*12 | T48: =SUM(E48:Q48)
B49: Peças de reposição para extintores e hidrantes e recargas eventuais | C49: 100 | D49: 150 | S49: =C49*12 | T49: =SUM(E49:Q49)
B50: Peças para Grupo Gerador, limpeza semestral filtro e óleo e óleo diesel | C50: 300 | D50: 500 | S50: =C50*12 | T50: =SUM(E50:Q50)
B51: Peças para manutenção das catracas | C51: 200 | D51: 350 | S51: =C51*12 | T51: =SUM(E51:Q51)
B53: DESPESAS ADMINISTRATIVAS | C53: 810 | D53: =SUM(D54:D59) | E53: =SUM(E54:E58) | F53: =SUM(F54:F58) | G53: =SUM(G54:G58) | H53: =SUM(H54:H58) | I53: =SUM(I54:I58) | J53: =SUM(J54:J58) | K53: =SUM(K54:K58) | L53: =SUM(L54:L58) | ... Q53: =SUM(Q54:Q58) | S53: =SUM(S54:S59) | T53: =SUM(T54:T59)
B54: Telefonia/Internet- apenas telefone, internet comodato | C54: 60 | D54: 250 | S54: =C54*12 | T54: =SUM(E54:Q54)
B55: Correio/Remessa Correspondências/Motoboy/Diversas | C55: 150 | D55: 150 | S55: =C55*12 | T55: =SUM(E55:Q55)
B56: Impostos - DIRF/DARF/ISSQN/PIS/COFINS | C56: 100 | D56: 170 | S56: =C56*12 | T56: =SUM(E56:Q56)
B57: Taxa Desepesas com Assembleia | C57: 50 | D57: 150 | S57: =C57*12 | T57: =SUM(E57:Q57)
B58: Custas Judiciais | C58: 100 | D58: 200 | S58: =C58*12 | T58: =SUM(E58:Q58)
A59: GOOGLE | B59: Hospedagem / Domínio Corporativo | C59: 100 | D59: 200 | S59: =C59*12 | T59: =SUM(E59:Q59)
B61: COTA | C61: 178671.02 | D61: =D3+D18+D28+D38+D53 | E61: =SUM(E3,E18,E28,E38,E53) | F61: =SUM(F3,F18,F28,F38,F53) | G61: =SUM(G3,G18,G28,G38,G53) | H61: =SUM(H3,H18,H28,H38,H53) | I61: =SUM(I3,I18,I28,I38,I53) | J61: =SUM(J3,J18,J28,J38,J53) | K61: =SUM(K3,K18,K28,K38,K53) | L61: =SUM(L3,L18,L28,L38,L53) | ... Q61: =SUM(Q3,Q18,Q28,Q38,Q53) | S61: =D61*12 | T61: =T3+T18+T28+T38+T53
B63: DESPESAS VARIÁVEIS | C63: R$ - | E63: =SUM(E64:E66) | F63: =SUM(F64:F66) | G63: =SUM(G64:G66) | H63: =SUM(H64:H66) | I63: =SUM(I64:I66) | J63: =SUM(J64:J66) | K63: =SUM(K64:K66) | L63: =SUM(L64:L66) | ... Q63: =SUM(Q64:Q66) | S63: =SUM(S64:S66) | T63: =SUM(T64:T66)
B64: Água e Esgoto - Área Comum | C64: - | T64: =SUM(E64:Q64)
B65: Energia Elétrica - Área Comum | C65: - | T65: =SUM(E65:Q65)
B66: Seguro fogo | C66: - | T66: =SUM(E66:Q66)
B68: OUTRAS DESPESAS | C68: R$ - | E68: =SUM(E69:E73) | F68: =SUM(F69:F73) | G68: =SUM(G69:G73) | H68: =SUM(H69:H73) | I68: =SUM(I69:I73) | J68: =SUM(J69:J73) | K68: =SUM(K69:K73) | L68: =SUM(L69:L73) | ... Q68: =SUM(Q69:Q73) | S68: =SUM(S69:S72) | T68: =SUM(T69:T73)
B69: Despesas Não Orçadas | C69: - | T69: =SUM(E69:Q69)
B70: Despesas reembolsáveis | S70: =C70*12 | T70: =SUM(E70:Q70)
B71: Honorários advocatícios | S71: =C71*12 | T71: =SUM(E71:Q71)
B72: Ampliação do CFTV | S72: =C72*12 | T72: =SUM(E72:Q72)
B73: Transferências Entre Contas | C73: -
B75: TOTAL DESPESAS CONTA PRINCIPAL | C75: 178671.02 | E75: =E68+E63+E61 | F75: =F68+F63+F61 | G75: =G68+G63+G61 | H75: =H68+H63+H61 | I75: =I68+I63+I61 | J75: =J68+J63+J61 | K75: =K68+K63+K61 | L75: =L68+L63+L61 | ... N75: =N68+N63+N61 | O75: =O61+O63+O68 | P75: =P61+P63+P68 | Q75: =Q68+Q63+Q61 | S75: =S61+S63+S68 | T75: =T61+T63+T68

Sheet PF 2023
D1: APROVADO
A2: EMPRESA | C2: PREVISÃO ORÇAMENTÁRIA - DIAMOND TOWER | D2: 2023 | E2: MARÇO | F2: ABRIL | G2: MAIO | H2: JUNHO | I2: JULHO | J2: AGOSTO | K2: SETEMBRO | L2: OUTUBRO | M2: NOVEMBRO | N2: DEZEMBRO | O2: JANEIRO | P2: FEVEREIRO | Q2: MARÇO | S2: PREVISTO | T2: REALIZADO
A3: JAN-MAI | B3: JUN-MAR | C3: CONTRATOS MÃO DE OBRA | D3: 133630.24 | E3: =SUM(E4:E16) | F3: =SUM(F4:F16) | G3: =SUM(G4:G16) | H3: =SUM(H4:H16) | I3: =SUM(I4:I16) | J3: =SUM(J4:J16) | K3: =SUM(K4:K16) | L3: =SUM(L4:L16) | ... Q3: =SUM(Q4:Q16) | S3: =SUM(S4:S16) | T3: =SUM(T4:T16)
A4: ONX SERVIÇOS | B4: ONX SERVIÇOS | C4: Monitoramento - 01 Posto 24h - Central de Segurança - ONX | D4: 112542 | E4: =84035.28+5002.1+11004.62 | F4: =78129.24+17099.88+4650.55+1017.85+12470.48 | G4: =96199.49+5726.16+12597.55 | H4: =95879.45+5707.11 | I4: =96170.08+5724.41+12593.7 | J4: =90802.13+5342.57+10706.66 | K4: =91180.66+5364.53+10745.32 | L4: =91326.14+5364.53+10599.84 | M4: =91183.25+5364.53+10742.73 | N4: =91070.48+5364.53+10855.49 | O4: =91213.96+5364.53+10712.02 | P4: =98141.45+5774.91+11581.87+559.75 | Q4: =97531.32+5736.92 | S4: =D4*11 | T4: =SUM(G4:Q10)
C5: Ronda Vigilante - 01 Posto 24h - ONX
C6: Porteiro 02 postos 8h - (Seg à Dom - das 7h as 22h) - ONX
C7: Expedição 01 posto 8h - (Seg à Sáb - das 08h às 16h20) - ONX
C8: Recepção - 04 postos 8h (das 7h as 22h) - ONX
C9: Limpeza - 03 Postos 44h semanais - ONX
C10: Serviços Gerais – 01 posto 44h semanais - ONX
B11: CAPPELLETTO | C11: Assistente Condominial 44h - Karoline Aguirres | I11: 0
A12: ORGÂNICO | B12: ORGÂNICO | C12: Oficial Manutenção - 01 Posto 44h semanais | D12: 5000 | E12: =2384+(718.82*0.3539)+441+39.49+(235.03*0.1086)+(5124.48*0.3346)+122+355.17+152.17+179.2+1119.21 | F12: =(671.82*0.3539)+441+39.49+(711.3*0.1086)+((842.87+659.65+1679.57+1199.37+209.94+16.79+125.96+25.19+167.95)/2)+83.97+(209.95/2)+433.43+441+2768+1086.51+206 | G12: =2678+(0.3539*757.64)+(458.94*FOLHA!C4)+39.49+94.7+236.77+413.86+441+990.64 | H12: =2531+(573.37*FOLHA!C3)+39.49+71.67+173.58+413.86+601+3046 | I12: =687.08+39.49+85.88+160.05+452.99+601+1717.7+1173.53+214.71+17.17+128.82+25.76+171.77 | J12: =6122+336.1+29.97+41.65+42.01+186.3+374.73+601+837.76+1173.53+104.72+8.37+62.83+12.56+83.77 | K12: =3574+41.65+41.54+168.8+413.86+601+817.7+1283.53+102.21+8.17+61.32+12.26+81.77 | L12: =3194+132+290.11+36.26+168.8+41.65+394.3+601+725.28+1173.53+90.66+7.25+54.39+10.87+72.52 | M12: =3196+290.36+41.65+1901.14+36.29+168.8+394.3+601 | N12: =3192+442.06+1414.11+41.65+36.24+159.52+168.8+219.18+4695.52+724.92+1173.53+90.61+7.24+54.36+10.87+72.49 | O12: =3211+443.18+41.65+74.4+168.8+394.3+601+729.65+1233.53+91.2+7.29+54.72+10.94+72.96 | P12: =1967+451.22+46.65+1094.07+1173.53+136.75+10.94+82.05+16.41+54.7+309.23+54.7+168.8+413.86+601 | Q12: =3324+291.09 | S12: =D12*11 | T12: =SUM(E12:Q12)
A13: GUARIDA | B13: GUARIDA | C13: Auxiliar Administração | D13: 2700 | E13: =66.57+115+2.49+1090+245.01+1365 | F13: =2.49+360+2.49+2.49+2.49+(3*2.49)+2.49+2.49+2.49+2.49+2.49+66.57+1090+245.01+1365+245.01+44.49 | G13: =2.49+2.49+2.49+2.49+2.49+2.49+2.49+2.49+66.57+2.49+1090+245.01+1365 | H13: =2.49+2.49+2.49+2.49+2.49+2.49+2.49+2.49+66.57+2.49+2.49+2.49+1090+150+245.01+2.49+1365+240 | I13: =2.49+2.49+2.49+2.49+2.49+2.49+2.49+2.49+2.49+2.49+2.49+66.57+2.49+1090+245.01+1365 | J13: =2.49+2.49+2.49+2.49+2.49+2.49+2.49+2.49+2.49+66.57+2.49+2.49+2.49+2.49+2.49+2.49+2.49+1090+245.01+1365 | K13: =2.49+2.49+2.49+2.49+2.49+2.49+2.49+2.49+66.57+2.49+2.49+2.49+2.49+2.49+2.49+2.49+2.49+2.49+1090+1365 | L13: =2.49+2.49+2.49+2.49+2.49+2.49+2.49+2.49+2.49+2.49+1090+245.01+1365+66.57 | M13: =66.57+1090+256.82+27.39+1430.79 | N13: =69.78+174+1090+180+256.82+32.37+1430.79 | O13: =69.78+1090+256.82+34.86+1430.79 | P13: =1090+256.82+22.41+1430.79 | S13: =D13*12 | T13: =SUM(E13:Q13)
A14: ORGÂNICO | B14: CAPPELLETTO | C14: Gestor Condominial - 01 Posto 44h semanais | D14: 7000 | E14: =3933+(716.82*0.6461)+441+39.49+(235.03*0.8914)+89.6+(5124.48*0.6654)+122+251.03+1846.37 | F14: =(671.82*0.6461)+441+39.49+(711.3*0.8914)+((842.87+659.65+1679.57+1199.37+209.94+16.79+125.96+25.19+167.95)/2)+(209.95/2)+441+4288+1792.43+339.83 | G14: =5028+(0.6461*757.64)+(0.8914*498.54)+39.49+441+1616.32 | H14: =3780+(573.37*FOLHA!B3)+39.49+11468.41 | I14: =6366.67+39.49 | J14: =16000 | K14: =16000 | L14: =16000 | M14: =16000 | N14: =16000+16000 | P14: =16000 | Q14: =16000 | S14: =D14*12 | T14: =SUM(E14:Q14)
A15: ORGÂNICO | B15: ORGÂNICO | C15: Remuneração Subsíndico | D15: 5222.24 | E15: =5222.24+2.49+645.44+931.06 | F15: =5222.24+842.87+659.65 | G15: =5222.24+ 719.51+677.82+645.44 | H15: =5222.24 | I15: =5222.24+240.67+745.97+645.44 | J15: =5222.24+63.83+412.34+645.44 | K15: =5222.24+180.59+398.3+705.94+645.44 | L15: =5222.24+173.64+338.22+645.44 | M15: =5222.24+645.44 | N15: =5222.24+94.83+338+645.44 | O15: =5222.24+979.08+269.76+340.84+645.44 | P15: =6093.62+96.4+584.66+645.44 | Q15: =6093.62 | S15: =D15*12 | T15: =SUM(E15:Q15)
A16: AUDI PASTAS | B16: AUDI PASTAS | C16: Auditoria Externa | D16: 1166 | E16: =22+1176+2.49 | F16: =24+1176 | G16: =24+1176+39 | H16: =24+1176 | I16: =24+1176 | J16: =24+1176 | K16: =24+1176 | L16: =24+66.57+1176 | M16: =26+1274 | N16: =26+1274 | O16: =26+1303.4 | P16: =26.6+1303.4 | Q16: =26.6 | S16: =D16*12 | T16: =SUM(E16:Q16)
C18: MANUTENÇÕES/LOCAÇÕES - CONTRATOS | D18: 27460.78 | E18: =SUM(E19:E25) | F18: =SUM(F19:F25) | G18: =SUM(G19:G25) | H18: =SUM(H19:H25) | I18: =SUM(I19:I25) | J18: =SUM(J19:J25) | K18: =SUM(K19:K25) | L18: =SUM(L19:L25) | ... Q18: =SUM(Q19:Q25) | S18: =SUM(S19:S26) | T18: =SUM(T19:T26)
A19: FG PISCINAS | C19: Limpeza Espelho D'água, Química e AFT com Material | D19: 850 | E19: =5+794 | F19: =6+794.75+67 | G19: =5.25+769.6+9.5+20.9 | H19: =9.5+782.4+12.1+5.5 | I19: =5.5+794.5+12.1 | J19: =5.5+771.2+19.8+9 | K19: =9+769.6+19.8+20.9+9.5 | L19: =9.5+777.6+20.9+15.4+7 | M19: =772.8+7.12+15.4+18.7+8.5 | N19: =8.5+782.4+12.1+5.5 | O19: =5.5+12.1+776 | P19: =7.59+16.5+771.2 | Q19: =9 | S19: =D19*12 | T19: =SUM(E19:Q19)
A20: SYSCOM | C20: Locação Impressora | D20: 223.82 | E20: =223.82 | F20: =223.82 | G20: =223.82 | H20: =223.82 | I20: =223.82 | J20: =223.82 | K20: =223.82 | L20: =223.82 | M20: =223.82 | N20: =141.75 | S20: =D20*12 | T20: =SUM(E20:Q20)
A21: BDS AR | C21: Manutenção ar condicionado / exaustão áreas comuns | D21: 3339.14 | E21: =3016.9+166.96+27.9+53.48+25.95+155.27 | F21: =3016.9+166.96+155.27 | G21: =3016.9+166.96+155.27+27.9 | H21: =3016.9+166.96+155.27 | I21: =3016.9+166.96+155.27 | J21: =3262.34+76.8+155.27 | K21: =3262.34+76.8 | L21: =3251.65+87.49 | M21: , | N21: =3220.93+118.21 | O21: =3205.24+133.9 | P21: =3315.52+147.16 | Q21: =3309.98+152.7 | S21: =D21*12 | T21: =SUM(E21:Q21)
A22: SYSCOM | C22: Manutenção CFTV/Controle de Acesso/Central Alarme | D22: 3536.46 | E22: =3437.79+98.67+11.16 | F22: =3437.79+98.67+11.16+972.1+27.9 | G22: =3437.79+98.67+27.9+972.1 | H22: =3437.79+98.67+27.9+972.1+105 | I22: =3437.79+369.5+98.67+27.9+972.1+369.5+24 | J22: =3437.79+27.9+98.67+972.1 | K22: =3437.79+98.67+27.9+972.1 | L22: =3437.79+98.67+27.9+972.1 | M22: =3437.79+98.67+27.9+260+615.66+17.67 | N22: =2177.26+17.67+62.49 | S22: =D22*12 | T22: =SUM(E22:Q22)
A23: ATLAS | C23: Manutenção Preventiva Elevadores (7) - Com Peças - Atlas | D23: 8680.97 | E23: =439.38+409.18+7950.43 | F23: =439.98+409.18+7950.43 | G23: =439.98+409.18+7950.43 | H23: =43.43+439.98+409.18+784.86+7950.43+40.39 | I23: =439.98+40.39+409.18+7950.43 | J23: =439.98+409.18+7950.43 | K23: =16.89+15.11+75.54+439.98+409.18+7950.43 | L23: =439.98+15.71+70.25+409.18+7950.43 | M23: =2.02+24.75+409.18+38.46+7950.43+439.98 | N23: =439.98+409.18+8333.7+428.91+461.19 | O23: =461.19+16.84+428.91 | P23: =461.19 | Q23: =461.19 | S23: =D23*12 | T23: =SUM(E23:Q23)
A24: ALTITUDE | C24: Limpeza da Fachada | D24: 7500 | E24: =5130+210+2.49+660 | F24: =5130+210+660 | G24: =5130+210+660 | M24: =439.98 | N24: =10440+1320+240 | O24: =10440+440+10440+1320+240 | P24: =240+240+2640+10440 | Q24: =240 | S24: =D24*12 | T24: =SUM(E24:Q24)
A25: STEMAC | C25: Manutenção preventiva motor gerador | D25: 1380.39 | E25: =1047.97+61.41+145.27+61.41+66.03 | F25: =1047.97+66.03+61.41+290.54+145.27 | G25: =1047.97+66.03+61.41+145.27 | H25: =66.039+1047.97+61.41+145.27 | I25: =1047.97+66.03+61.41+145.27 | J25: =1047.97+66.03+61.41+145.27 | K25: =1047.97+66.03+61.41+145.27 | L25: =1047.97+66.03+61.41+145.27 | M25: =1047.97+66.03+61.41+145.27 | N25: =1047.97+66.03+61.41+1047.97+145.27 | O25: =66.03+61.41+61.41+145.27 | P25: =1096.19+69.07+151.95 | Q25: =1096.19+69.07 | S25: =D25*12 | T25: =SUM(E25:Q25)
A26: BELLINI | C26: Consultoria jurídica | D26: 1950 | E26: =1911+39+2.49 | F26: =1911+39 | G26: =1911+39 | H26: =1911+39 | I26: =1908.27+41.73 | J26: =1908.27+41.73 | K26: =1908.07+41.93 | L26: =1908.07+41.93 | M26: =1907.68+42.32 | N26: =2581.39+58.61 | O26: =2580.34+59.66 | P26: =2763.57+60.43 | Q26: =2763.28+43 | S26: =D26*12 | T26: =SUM(E26:Q26)
C28: MANUTENÇÕES - SEM CONTRATO | D28: 10450 | E28: =SUM(E29:E36) | F28: =SUM(F29:F36) | G28: =SUM(G29:G36) | H28: =SUM(H29:H36) | I28: =SUM(I29:I36) | J28: =SUM(J29:J36) | K28: =SUM(K29:K36) | L28: =SUM(L29:L36) | ... Q28: =SUM(Q29:Q36) | S28: =SUM(S29:S36) | T28: =SUM(T29:T36)
A29: MULTIPLAN | C29: Lixo/Entulho/Manutenção Externa - Despesa Compartilhada | D29: 3000 | E29: =1211.64+609.89 | G29: =1641.17 | H29: =1476.48 | I29: =2191.21 | J29: =2415.11 | K29: =1981.04 | L29: =1680.44 | M29: =2073.15+2125.41 | O29: =1139.49+1509.89 | S29: =D29*12 | T29: =SUM(E29:Q29)
A30: DEMANDA | C30: Manutenção Bombas de Recalque | D30: 500 | F30: =1273+67 | L30: =495 | M30: =495+630 | N30: =630 | O30: =660 | S30: =D30*12 | T30: =SUM(E30:Q30)
C31: Manutenção Interfones | D31: 50 | E31: =388.84+366.33 | F31: =275 | J31: =390 | N31: =294+6 | O31: =6+270.2+270.2+270.2+9.8 | P31: =9.8+9.8+9.8 | S31: =D31*12 | T31: =SUM(E31:Q31)
C32: Manutenção Predial | D32: 3000 | E32: =4338+2.49 | F32: =191.9+329+3374+80+2.49 | G32: =165.4+3374 | H32: =947.5+174.73+5.27 | I32: =5.27+880 | J32: =422.1 | K32: =3781.8+178.2 | L32: =2710+368.76+11.24 | M32: =11.24+69.99 | O32: =570 | P32: =4302.63+30+341.25+75+1500 | Q32: =286 | S32: =D32*12 | T32: =SUM(E32:Q32)
C33: Manutenção Preventiva Sistema de Incêndio | D33: 300 | S33: =D33*12 | T33: =SUM(E33:Q33)
C34: Obrigações Legais (AFT, certificado de qualidade do ar de ambiente climatizado, certificado digital, inspeção da esccada pressurizada, laudo de potabilidade, teste mangueiras, recarga extintores, SPDA, subestação de energia) | D34: 3000 | E34: =1200+16.5+15.35+2.49 | F34: =132.3+2.7 | G34: =2.7+132.3+612.3+291.5+123.23+26.5 | H34: =176.4+8338+2.7+3374+3.6 | I34: =3.6+132.3+298.16+2.7+16.5+15.35 | J34: =16.5+15.35 | K34: =3216.45+1200 | L34: =272.57+290+2400+96.62 | M34: =2400+121.69+2.48 | N34: =2.48+230+121.69+264.6+5.4 | O34: =118.75+5.4+2.48+6.25+121.69+2460 | P34: =121.69+2.48+325.26 | Q34: =18+2.48+121.69 | S34: =D34*12 | T34: =SUM(E34:Q34)
C35: Controle Pragas e Limpeza Caixa D'água (2x ano) | D35: 500 | G35: =291.5 | H35: =2208.78 | I35: =123.23+26.5 | N35: =825.1+245.3+44.6 | O35: =44.6+1115+245.3 | S35: =D35*12 | T35: =SUM(E35:Q35)
C36: Paisagismo interno | D36: 100 | I36: =1111.31 | S36: =D36*12 | T36: =SUM(E36:Q36)
C38: MATERIAIS E EQUIPAMENTOS | D38: 6320 | E38: =SUM(E39:E51) | F38: =SUM(F39:F51) | G38: =SUM(G39:G51) | H38: =SUM(H39:H51) | I38: =SUM(I39:I51) | J38: =SUM(J39:J51) | K38: =SUM(K39:K51) | L38: =SUM(L39:L51) | ... Q38: =SUM(Q39:Q51) | S38: =SUM(S39:S51) | T38: =SUM(T39:T51)
A39: DEMANDA | C39: Cartões para controle de acesso | D39: 200 | E39: =1088 | F39: =371 | H39: =799 | J39: =167.1 | K39: =237.5 | N39: =781 | S39: =D39*12 | T39: =SUM(E39:Q39)
C40: Chaveiro | D40: 20 | H40: =100 | I40: 10 | N40: =220+40+20 | S40: =D40*12 | T40: =SUM(E40:Q40)
C41: Lâmpadas | D41: 500 | K41: =439.5+71.61 | S41: =D41*12 | T41: =SUM(E41:Q41)
C42: Materiais/Serviços Obras Diversas (Alvenaria, Serralheria, Funilaria, Outros) | D42: 600 | H42: =613.9+128.05 | I42: =330+350.1+432+46.9+18 | J42: =547.6+437.9+18+722.6+506.4+136.4+489.5+175+60.5 | K42: =313.55+337.8+28.45+56.9+145+70.1 | L42: =496.05+120 | M42: =391.95 | N42: =124.8+320.8+621.35 | S42: =D42*12 | T42: =SUM(E42:Q42)
C43: Material de Ferragem (Elétrica, Hidráulica e Ferramentas) | D43: 600 | E43: =298.45+93.45+159.9+183.75+29.5+76.4+189.9+0.99+200+344 | F43: =216.85+786.16+143.97+344+409.45+184+379.9+94.05+184+786.17+181.9+35.3+117.4+142.1 | G43: =344+786.17+51.4+216 | H43: =42.8+498.2+330+134.05+67.1+100+64.8+71.4 | I43: =443.2+546.85+110.7+66.53 | J43: =1250+330+24.4+383.7+106.68+100.8+29.9+5.64+95.88 | K43: =27.05+151.91+1140 | L43: =283.17+54.61 | M43: =355.9+60.1+487.3 | N43: =355.9+195.75 | O43: =156.6+19.35 | P43: =437.15+31.5+527.29 | Q43: =56.91+88.15+28.98+43 | S43: =D43*12 | T43: =SUM(E43:Q43)
C44: Material Expediente Interno | D44: 300 | F44: =71.34+229.81+343.2 | H44: =299.31+321.6+339.9 | I44: =434.72 | J44: =310.31+51.15 | K44: =138.8+139.2 | L44: =414.81+24.9 | M44: =367.5+73.35+55.4 | N44: =272.91+52.9 | O44: =327.64+145.9 | P44: =108.72 | S44: =D44*12 | T44: =SUM(E44:Q44)
C45: Material Limpeza/Consumíveis | D45: 2000 | E45: =366.6+246.56+371.57+1356.12 | F45: =924.02 | G45: =32.58+1548.91 | H45: =1067.31+61.45 | I45: =770.65+151.32+477.33+436.59+841.9 | J45: =500.32+591.04 | K45: =175.38+498.34+730.55 | L45: =453.28+970.87+715.9+226.6 | M45: =383.94+632.21 | N45: =341.98+876.48 | O45: =765.15+616.73 | P45: =659.3+606.98 | Q45: =115.3 | S45: =D45*12 | T45: =SUM(E45:Q45)
A46: ATLAS | C46: Peças elevador | D46: 500 | K46: =305.18+1364.99+16.89+15.71+70.25 | N46: =445.5+447.15+273.03+22.93+24.65+23.01+24.75+14.05+15.11 | O46: =304.27+14.05+22.93+23.01+15.66+16.84 | P46: =694.2 | S46: =D46*12 | T46: =SUM(E46:Q46)
A47: DEMANDA | C47: Móveis e Utensílios | D47: 500 | E47: 665.89 | F47: =1598 | G47: =449.9+2066.97 | I47: =399 | J47: =150 | L47: =1934.1 | M47: =459.8+2549.91 | O47: =25.46 | P47: =591.88 | S47: =D47*12 | T47: =SUM(E47:Q47)
C48: Peças Ar Condicionado/Exaustores | D48: 500 | J48: =100 | K48: 1400 | L48: =1400 | Q48: =1200 | S48: =D48*12 | T48: =SUM(E48:Q48)
C49: Peças de reposição para extintores e hidrantes e recargas eventuais | D49: 100 | S49: =D49*12 | T49: =SUM(E49:Q49)
C50: Peças para Grupo Gerador, limpeza semestral filtro e óleo e óleo diesel | D50: 300 | F50: =1642.5 | O50: =295.01 | P50: =2101 | S50: =D50*12 | T50: =SUM(E50:Q50)
C51: Peças para manutenção das catracas | D51: 200 | F51: =750 | O51: =506.06 | S51: =D51*12 | T51: =SUM(E51:Q51)
C53: DESPESAS ADMINISTRATIVAS | D53: 810 | E53: =SUM(E54:E60) | F53: =SUM(F54:F60) | G53: =SUM(G54:G60) | H53: =SUM(H54:H60) | I53: =SUM(I54:I60) | J53: =SUM(J54:J60) | K53: =SUM(K54:K60) | L53: =SUM(L54:L60) | ... Q53: =SUM(Q54:Q60) | S53: =SUM(S54:S61) | T53: =SUM(T54:T61)
C54: Telefonia/Internet- apenas telefone, internet comodato | D54: 60 | E54: =55.03 | F54: =52.41 | G54: =54.55+30 | H54: =57.78+43.4 | I54: =61.86+99.98 | J54: =62.72+75 | K54: =49.26+49.99 | L54: =50.87+49.99 | M54: =54.25+49.99 | N54: =69.45+49.99 | O54: =45.56 | P54: =48.57+49.99+49.99 | Q54: =50.63 | S54: =D54*12 | T54: =SUM(E54:Q54)
C55: Impressões/Cópias | D55: 50 | S55: =D55*12 | T55: =SUM(E55:Q55)
C56: Correio/Remessa Correspondências/Motoboy/Diversas | D56: 150 | E56: =226.21+29.93+2.49 | F56: =29.99 | J56: =27.7 | N56: =50+12+308.34 | O56: =95.36 | S56: =D56*12 | T56: =SUM(E56:Q56)
C57: Impostos - DIRF/DARF/ISSQN/PIS/COFINS | D57: 100 | E57: =46+66.03+2.7+55.8+520 | F57: =2.7+55.8+345 | G57: =55.8 | H57: =55.8 | I57: =55.8 | J57: =55.8 | K57: =55.8 | L57: =55.8 | M57: =24.65+55.8 | N57: =62.49+55.8 | O57: =55.8 | P57: =55.8 | Q57: =2.02+25.44+24.75 | S57: =D57*12 | T57: =SUM(E57:Q57)
C58: Material Expediente | D58: 200 | G58: =412.09 | S58: =D58*12 | T58: =SUM(E58:Q58)
C59: Taxa Desepesas com Assembleia | D59: 50 | I59: =229.67 | J59: =580 | S59: =D59*12 | T59: =SUM(E59:Q59)
C60: Custas Judiciais | D60: 100 | I60: =1615.5 | K60: =183.39+769.83 | M60: =253.9+253.9 | O60: =400 | P60: =318.5 | S60: =D60*12 | T60: =SUM(E60:Q60)
A61: GOOGLE | C61: Hospedagem / Domínio Corporativo | D61: 100 | E61: =72.9+2.49 | F61: =145.8 | G61: =301.76 | J61: =104.52 | K61: =108 | L61: =131.4 | M61: =135 | O61: =522 | S61: =D61*12 | T61: =SUM(E61:Q61)
C63: COTA | D63: 178671.02 | E63: =SUM(E3,E18,E28,E38,E53) | F63: =SUM(F3,F18,F28,F38,F53) | G63: =SUM(G3,G18,G28,G38,G53) | H63: =SUM(H3,H18,H28,H38,H53) | I63: =SUM(I3,I18,I28,I38,I53) | J63: =SUM(J3,J18,J28,J38,J53) | K63: =SUM(K3,K18,K28,K38,K53) | L63: =SUM(L3,L18,L28,L38,L53) | ... Q63: =SUM(Q3,Q18,Q28,Q38,Q53) | S63: =D63*12 | T63: =T3+T18+T28+T38+T53
C65: DESPESAS VARIÁVEIS | D65: R$ - | E65: =SUM(E66:E68) | F65: =SUM(F66:F68) | G65: =SUM(G66:G68) | H65: =SUM(H66:H68) | I65: =SUM(I66:I68) | J65: =SUM(J66:J68) | K65: =SUM(K66:K68) | L65: =SUM(L66:L68) | ... Q65: =SUM(Q66:Q68) | S65: =SUM(S66:S68) | T65: =SUM(T66:T68)
C66: Água e Esgoto - Área Comum | D66: - | E66: =12123.05 | F66: =13289.7 | G66: 11734.08 | H66: =9100.72 | I66: =9100.73 | J66: 9100.72 | K66: =9100.72 | L66: =9100.72 | M66: =9100.72 | N66: =9100.72 | O66: =9552.81 | P66: =9552.81 | T66: =SUM(E66:Q66)
C67: Energia Elétrica - Área Comum | D67: - | E67: =22347.4+21815.92 | F67: =25787.87 | G67: 20668.88 | H67: =19808.74 | I67: 19746.62 | J67: =20184.1 | K67: =20351.49 | L67: =18611.35 | M67: =20702.17 | O67: =19806.91+22880.06 | P67: =25959.17 | T67: =SUM(E67:Q67)
C68: Seguro fogo | D68: - | J68: =6637.96 | K68: =6637.96 | L68: =6637.96 | M68: =6637.96 | N68: =6637.96 | O68: =6638.04 | T68: =SUM(E68:Q68)
C70: OUTRAS DESPESAS | D70: R$ - | E70: =SUM(E71:E75) | F70: =SUM(F71:F75) | G70: =SUM(G71:G75) | H70: =SUM(H71:H75) | I70: =SUM(I71:I75) | J70: =SUM(J71:J75) | K70: =SUM(K71:K75) | L70: =SUM(L71:L75) | ... Q70: =SUM(Q71:Q75) | S70: =SUM(S71:S74) | T70: =SUM(T71:T75)
C71: Despesas Não Orçadas | D71: - | E71: =44859.2+2.49 | G71: =1100+6198 | H71: =768.12+13191.7 | I71: =1710+592.1 | J71: =13002.8+252.59 | K71: =12957+180 | L71: =48.18+28.52+17.94+211.82 | M71: =87.25+5.31 | N71: =688.98 | O71: =45.5+73.5+12665.14 | P71: =9104.2+3820+50.85 | Q71: =180 | T71: =SUM(E71:Q71)
C72: Despesas reembolsáveis | E72: =969.26+98.91+26.99+3.94+39.31+39.31+19.78+2387.37+969.26+1926.1+1917.4+0.6+64.9+2.49+2.49+2.49+2.49+2.49+2.49+48.73 | H72: =48.73+39.31+39.13+1193.98+24.37 | I72: =24.37+1193.98+287.32+716.49+157.7+292.38+5.86+14.62+5.97+3.22 | J72: =24.37+5.86+14.62+3.22+5.97+157.7+292.38+1200 | K72: =3.22+5.97+41.93+53.75+157.7+292.38+440.93+9 | L72: =3.22+5.97+9+292.38 | M72: =5.97+52.08+257.89+5.26 | N72: =5.26 | O72: =1199.7+45.15+192.08+694.2+45.15 | S72: =D72*12 | T72: =SUM(E72:Q72)
C73: Honorários advocatícios | F73: =1926.1+1917.4+1193.98+969.26+48.73+19.78+39.31+39.13+24.37 | G73: =2387.97+1926.1+1917.4+19.78+39.31+39.13+24.37+48.73 | J73: =2446.25+53.75 | K73: =2446.25+53.75 | M73: =2347.92+52.08 | N73: =1955.6+44.4 | O73: =1954.8+45.2 | P73: =1957.2+978.6+978.6+1500+42.8+21.4+21.4 | Q73: =978.5+978.5+1957+21.5+21.5+60.72 | S73: =D73*12 | T73: =SUM(E73:Q73)
C74: Ampliação do CFTV | H74: =53640.8+36290+1710 | J74: =3820+180 | M74: =13028.1 | O74: =11875.7+1079.15 | S74: =D74*12 | T74: =SUM(E74:Q74)
C75: Transferências Entre Contas | D75: -
C77: TOTAL DESPESAS CONTA PRINCIPAL | D77: 178671.02 | E77: =E70+E65+E63 | F77: =F70+F65+F63 | G77: =G70+G65+G63 | H77: =H70+H65+H63 | I77: =I70+I65+I63 | J77: =J70+J65+J63 | K77: =K70+K65+K63 | L77: =L70+L65+L63 | ... N77: =N70+N65+N63 | O77: =O63+O65+O70 | P77: =P63+P65+P70 | Q77: =Q70+Q65+Q63 | S77: =S63+S65+S70 | T77: =T63+T65+T70

Sheet RS 2023
C2: RESUMO DE SALDOS
C3: 2023 | O3: 2024
B4: CONTA | C4: MARÇO | D4: ABRIL | E4: MAIO | F4: JUNHO | G4: JULHO | H4: AGOSTO | I4: SETEMBRO | J4: OUTUBRO | K4: NOVEMBRO | L4: DEZEMBRO | M4: JANEIRO | N4: FEVEREIRO | O4: MARÇO
B6: PRINCIPAL | C6: =C10 | D6: =D10 | E6: =E10 | F6: =F10 | G6: =G10 | H6: =H10 | I6: =I10 | J6: =J10 | ... O6: =O10
B7: SALDO ANTERIOR | C7: 552132.31 | D7: 518555.69 | E7: 484561.61 | F7: 472986.01 | G7: 339156.69 | H7: 340258.29 | I7: 292874.23 | J7: 252914.22 | K7: 215637.61 | L7: 173288.69 | M7: 137999.8 | N7: 66531.92 | O7: 16871.3
B8: RECEITA | C8: 247222.65 | D8: 186460.07 | E8: 213554.72 | F8: 195997.96 | G8: 206150.02 | H8: 185455.19 | I8: 195221.23 | J8: 188175.79 | K8: 187343.88 | L8: 187237.82 | M8: 186984.33 | N8: 189944.3 | O8: 170494.4
B9: DESPESA | C9: -280799.27 | D9: -220454.15 | E9: -225130.32 | F9: -329827.28 | G9: -205048.42 | H9: -232839.25 | I9: -235181.24 | J9: -225452.4 | K9: -229692.8 | L9: -222526.71 | M9: -258452.21 | N9: -239604.92 | O9: -143309.03
B10: SALDO ATUAL | C10: =SUM(C7:C9) | D10: =SUM(D7:D9) | E10: =SUM(E7:E9) | F10: =SUM(F7:F9) | G10: =SUM(G7:G9) | H10: =SUM(H7:H9) | I10: =SUM(I7:I9) | J10: =SUM(J7:J9) | ... O10: =SUM(O7:O9)
B12: SALA DE EVENTOS | C12: =C16 | D12: =D16 | E12: =E16 | F12: =F16 | G12: =G16 | H12: =H16 | I12: =I16 | J12: =J16 | ... O12: =O16
B13: SALDO ANTERIOR | C13: 89545.4 | D13: 94155.73 | E13: 96169.51 | F13: 107107.5 | G13: 113362.57 | H13: 120417.49 | I13: 129809.63 | J13: 136072.31 | K13: 144597.31 | L13: 148872.31 | M13: 156740.39 | N13: 167182.08 | O13: 174810.85
B14: RECEITA | C14: 4610.33 | D14: 2013.78 | E14: 10937.99 | F14: 6455.07 | G14: 7054.92 | H14: 9392.14 | I14: 6262.68 | J14: 8525 | K14: 4275 | L14: 7868.08 | M14: 10441.69 | N14: 7628.77 | O14: 6900
B15: DESPESA | C15: 0 | D15: 0 | E15: 0 | F15: -200 | G15: 0 | H15: 0 | I15: 0 | J15: 0 | K15: 0 | L15: 0 | M15: 0 | N15: 0 | O15: 0
B16: SALDO ATUAL | C16: =SUM(C13:C15) | D16: =SUM(D13:D15) | E16: =SUM(E13:E15) | F16: =SUM(F13:F15) | G16: =SUM(G13:G15) | H16: =SUM(H13:H15) | I16: =SUM(I13:I15) | J16: =SUM(J13:J15) | ... O16: =SUM(O13:O15)
B18: ESTACIONAMENTO | C18: =C22 | D18: =D22 | E18: =E22 | F18: =F22 | G18: =G22 | H18: =H22 | I18: =I22 | J18: =J22 | ... O18: =O22
B19: SALDO ANTERIOR | C19: 61475.76 | D19: 70685.27 | E19: 79909.25 | F19: 89732.25 | G19: 100391.25 | H19: 110214.25 | I19: 120277.88 | J19: 131363.86 | K19: 144340.71 | L19: 154804.8 | M19: 167995.81 | N19: 180970.34 | O19: 193938.04
B20: RECEITA | C20: 9209.51 | D20: 9223.98 | E20: 10032 | F20: 10659 | G20: 9823 | H20: 10063.63 | I20: 11085.98 | J20: 12976.85 | K20: 10464.09 | L20: 13191.01 | M20: 12974.53 | N20: 12967.7 | O20: 12958
B21: DESPESA | C21: 0 | D21: 0 | E21: -209 | F21: 0 | G21: 0 | H21: 0 | I21: 0 | J21: 0 | K21: 0 | L21: 0 | M21: 0 | N21: 0 | O21: 0
B22: SALDO ATUAL | C22: =SUM(C19:C21) | D22: =SUM(D19:D21) | E22: =SUM(E19:E21) | F22: =SUM(F19:F21) | G22: =SUM(G19:G21) | H22: =SUM(H19:H21) | I22: =SUM(I19:I21) | J22: =SUM(J19:J21) | ... O22: =SUM(O19:O21)
B24: INADIMPLÊNCIA | C24: =C26 | D24: =D26 | E24: =E26 | F24: =F26 | G24: =G26 | H24: =H26 | I24: =I26 | J24: =J26 | ... O24: =O26
B25: SALDO ANTERIOR | C25: 6358.97 | D25: 6358.97 | E25: 6358.97 | F25: 6358.97 | G25: 6358.97 | H25: 6358.97 | I25: 6358.97 | J25: 6358.97 | K25: 6358.97 | L25: 6358.97 | M25: 6358.97 | N25: 6358.97 | O25: 6358.97
B26: SALDO ATUAL | C26: 6358.97 | D26: 6358.97 | E26: 6358.97 | F26: 6358.97 | G26: 6358.97 | H26: 6358.97 | I26: 6358.97 | J26: 6358.97 | K26: 6358.97 | L26: 6358.97 | M26: 6358.97 | N26: 6358.97 | O26: 6358.97
B28: FUNDO DE RESERVA | C28: =C30 | D28: =D30 | E28: =E30 | F28: =F30 | G28: =G30 | H28: =H30 | I28: =I30 | J28: =J30 | ... O28: =O30
B29: SALDO ANTERIOR | C29: 4522.65 | D29: 4522.65 | E29: 4522.65 | F29: 4522.65 | G29: 4522.65 | H29: 4522.65 | I29: 4522.65 | J29: 4522.65 | K29: 4522.65 | L29: 4522.65 | M29: 4522.65 | N29: 4522.65 | O29: 4522.65
B30: SALDO ATUAL | C30: 4522.65 | D30: 4522.65 | E30: 4522.65 | F30: 4522.65 | G30: 4522.65 | H30: 4522.65 | I30: 4522.65 | J30: 4522.65 | K30: 4522.65 | L30: 4522.65 | M30: 4522.65 | N30: 4522.65 | O30: 4522.65
B32: BRADESCO | C32: =C34 | D32: =D34 | E32: =E34 | F32: =F34 | G32: =G34 | H32: =H34 | I32: =I34 | J32: =J34 | ... O32: =O34
B33: SALDO ANTERIOR | C33: =114858.61+941415.06 | D33: =C34 | E33: =D34 | F33: =E34 | G33: =F34 | H33: =G34 | I33: =H34 | J33: =I34 | K33: =J34 | ... O33: =N34
B34: SALDO ATUAL | C34: 1116354.1 | D34: 1158621.6 | E34: 1163592.5 | F34: 1168388.3 | G34: 1173234.4 | H34: 1178438.4 | I34: =373804.8+125711.09+352415.05+331009.4 | J34: =126847.01+731502.06+331009.4 | K34: =127901.57+738206.99+331009.4 | L34: =128939.98+744814.94+331009.4 | M34: =130068.97+752005.51+331009.4 | N34: =130417.64+758028.89+331009.4 | O34: 1228991.3
B36: TOTAL | C36: =C6+C12+C18+C24+C28+C32 | D36: =D6+D12+D18+D24+D28+D32 | E36: =E6+E12+E18+E24+E28+E32 | F36: =F6+F12+F18+F24+F28+F32 | G36: =G6+G12+G18+G24+G28+G32 | H36: =H6+H12+H18+H24+H28+H32 | I36: =I6+I12+I18+I24+I28+I32 | J36: =J6+J12+J18+J24+J28+J32 | ... O36: =O6+O12+O18+O24+O28+O32

Sheet DC
A1: PROJEÇÃO | J1: REALIZADO
A2: ANO | B2: MÊS | C2: SALDO ANTERIOR | D2: COTA | E2: ESTAC | F2: REUNIÕES | G2: DESPESA | H2: CFTV | J2: ANO | K2: MÊS | L2: SALDO ANTERIOR | M2: RECEITA COTA | N2: ESTAC | O2: REUNIÕES | P2: DESPESA | Q2: CFTV
A3: 2023 | B3: março | C3: 713969.29 | D3: 151804.81 | E3: 8000 | F3: 4000 | G3: -180000 | H3: -24587.5 | J3: 2023 | K3: março | L3: 713969.29 | M3: 247222.65 | N3: 9209.51 | O3: 4610.33 | P3: =-280799.27 | Q3: -
B4: abril | C4: =SUM(C3:H3) | D4: 151804.81 | E4: 8000 | F4: 4000 | G4: -180000 | H4: -24587.5 | K4: abril | L4: =SUM(L3:Q3) | M4: 186460.07 | N4: 9223.98 | O4: 2013.78 | P4: -220454.15 | Q4: -
B5: maio | C5: =SUM(C4:H4) | D5: 151804.81 | E5: 8000 | F5: 4000 | G5: -180000 | H5: -24587.5 | K5: maio | L5: =SUM(L4:Q4) | M5: 213554.72 | N5: 10032 | O5: 10937.99 | P5: =-225371.9+32.58
B6: junho | C6: =SUM(C5:H5) | D6: 151804.81 | E6: 8000 | F6: 4000 | G6: -180000 | H6: -24587.5 | K6: junho | L6: =SUM(L5:Q5) | M6: 195997.96 | N6: 10659 | O6: 6455.07 | P6: -330027.28
B7: julho | C7: =SUM(C6:H6) | D7: 151804.81 | E7: 8000 | F7: 4000 | G7: -180000 | K7: julho | L7: =SUM(L6:Q6) | M7: 206150.02 | N7: 9823 | O7: 7054.92 | P7: -205048.42
B8: agosto | C8: =SUM(C7:H7) | D8: 151804.81 | E8: 8000 | F8: 4000 | G8: -180000 | K8: agosto | L8: =SUM(L7:Q7) | M8: 185455.19 | N8: 10063.63 | O8: 9392.14 | P8: -232839.25
B9: setembro | C9: =SUM(C8:H8) | D9: 151804.81 | E9: 8000 | F9: 4000 | G9: -180000 | K9: setembro | L9: =SUM(L8:Q8) | M9: 195221.23 | N9: 11085.98 | O9: 6262.68 | P9: -235181.24
B10: outubro | C10: =SUM(C9:H9) | D10: 151804.81 | E10: 8000 | F10: 4000 | G10: -180000 | K10: outubro | L10: =SUM(L9:Q9) | M10: 188175.79 | N10: 12976.85 | O10: 8525 | P10: -225452.4
B11: novembro | C11: =SUM(C10:H10) | D11: 151804.81 | E11: 8000 | F11: 4000 | G11: -180000 | K11: novembro | L11: =SUM(L10:Q10) | M11: 187343.88 | N11: 10464.09 | O11: 4275 | P11: -229692.8
B12: dezembro | C12: =SUM(C11:H11) | D12: 151804.81 | E12: 8000 | F12: 4000 | G12: -180000 | K12: dezembro | L12: =SUM(L11:Q11) | M12: 187237.82 | N12: 13191.01 | O12: 7868.08 | P12: -222526.71
A13: 2024 | B13: janeiro | C13: =SUM(C12:H12) | D13: 151804.81 | E13: 8000 | F13: 4000 | G13: -180000 | J13: 2024 | K13: janeiro | L13: =SUM(L12:Q12) | M13: 186984.33 | N13: 12974.53 | O13: 10441.69 | P13: -258452.21
B14: fevereiro | C14: =SUM(C13:H13) | D14: 151804.81 | E14: 8000 | F14: 4000 | G14: -180000 | K14: fevereiro | L14: =SUM(L13:Q13) | M14: 189944.3 | N14: 12967.7 | O14: 7628.77 | P14: -239604.92
B15: março | C15: =SUM(C14:H14) | D15: - | E15: - | F15: - | G15: -180000 | K15: março | L15: =SUM(L14:Q14)
D19: =C3-C15

Sheet RS 2022
B1: RESUMO DE SALDOS
B2: 2022 | N2: 2023
A3: CONTA | B3: JANEIRO | C3: FEVEREIRO | D3: MARÇO | E3: ABRIL | F3: MAIO | G3: JUNHO | H3: JULHO | I3: AGOSTO | J3: SETEMBRO | K3: OUTUBRO | L3: NOVEMBRO | M3: DEZEMBRO | N3: JANEIRO | O3: FEVEREIRO | P3: MARÇO
A5: PRINCIPAL | B5: =B9 | C5: =C9 | D5: =D9 | E5: =E9 | F5: =F9 | G5: =G9 | H5: =H9 | I5: =I9 | ... P5: =P9 | R5: =O5+O11+O17+O23+O27
A6: SALDO ANTERIOR | B6: 596624.76 | C6: =B9 | D6: =C9 | E6: =D9 | F6: =E9 | G6: =F9 | H6: =G9 | I6: =H9 | J6: =I9 | K6: =J9 | L6: 0 | M6: =L9 | N6: =M9 | O6: =N9 | P6: =O9
A7: RECEITA | B7: 197663.32 | C7: 188366.85 | D7: 189788.6 | E7: 182087.05 | F7: 184206.22 | G7: 217398.91 | H7: 232569.98 | I7: 260316.89 | J7: 282731.33 | K7: 252750.56 | L7: =414839.79 | M7: 312497.63 | N7: 280595.02 | O7: 204744.74
A8: DESPESA | B8: -275101.92 | C8: -662760.09 | D8: -208990.8 | E8: -195547.4 | F8: -210961.1 | G8: -191546.65 | H8: -186980.45 | I8: -204512.59 | J8: -180953.05 | K8: -190915.7 | L8: -105700.48 | M8: -210963.83 | N8: -187580.75 | O8: -156299.81
A9: SALDO ATUAL | B9: =SUM(B6:B8) | C9: =SUM(C6:C8) | D9: =SUM(D6:D8) | E9: =SUM(E6:E8) | F9: =SUM(F6:F8) | G9: =SUM(G6:G8) | H9: =SUM(H6:H8) | I9: =SUM(I6:I8) | ... P9: =SUM(P6:P8)
A11: SALA DE EVENTOS | B11: =B15 | C11: =C15 | D11: =D15 | E11: =E15 | F11: =F15 | G11: =G15 | H11: =H15 | I11: =I15 | ... P11: =P15
A12: SALDO ANTERIOR | B12: 43351.01 | C12: =B15 | D12: =C15 | E12: =D15 | F12: =E15 | G12: =F15 | H12: =G15 | I12: =H15 | J12: =I15 | ... P12: =O15
A13: RECEITA | B13: 3100 | C13: 1900 | D13: 2100 | E13: 1600 | F13: 4300 | G13: 4300 | H13: 2600 | I13: 3450 | J13: 4220.91 | K13: 3500 | L13: =71371.92-L12 | M13: 8005.11 | N13: 5660.17 | O13: 4508.2
A14: DESPESA | B14: 0 | C14: 0 | D14: 0 | E14: 0 | F14: 0 | G14: 0 | H14: -5900 | I14: 0 | J14: -200 | K14: 0 | L14: 0 | M14: 0 | N14: 0 | O14: 0
A15: SALDO ATUAL | B15: =SUM(B12:B14) | C15: =SUM(C12:C14) | D15: =SUM(D12:D14) | E15: =SUM(E12:E14) | F15: =SUM(F12:F14) | G15: =SUM(G12:G14) | H15: =SUM(H12:H14) | I15: =SUM(I12:I14) | ... P15: =SUM(P12:P14)
A17: ESTACIONAMENTO | B17: =B21 | C17: =C21 | D17: =D21 | E17: =E21 | F17: =F21 | G17: =G21 | H17: =H21 | I17: =I21 | ... P17: =P21
A18: SALDO ANTERIOR | B18: 171252.87 | C18: =B21 | D18: =C21 | E18: =D21 | F18: =E21 | G18: =F21 | H18: =G21 | I18: =H21 | J18: =I21 | ... P18: =O21
A19: RECEITA | B19: 6479 | C19: 6061 | D19: 6479 | E19: 6688 | F19: 6897 | G19: 7524 | H19: 7315 | I19: 7524 | J19: 8327.14 | K19: 9581 | L19: =34038.26-L18 | M19: 9210.83 | N19: 10263.2 | O19: 7963.47
A20: DESPESA | B20: 0 | C20: -183792.87 | D20: 0 | E20: 0 | F20: 0 | G20: -17328.44 | H20: -17328.44 | I20: 0 | J20: 0 | K20: 0 | L20: 0 | M20: 0 | N20: 0 | O20: 0
A21: SALDO ATUAL | B21: =SUM(B18:B20) | C21: =SUM(C18:C20) | D21: =SUM(D18:D20) | E21: =SUM(E18:E20) | F21: =SUM(F18:F20) | G21: =SUM(G18:G20) | H21: =SUM(H18:H20) | I21: =SUM(I18:I20) | ... P21: =SUM(P18:P20)
A23: INADIMPLÊNCIA | B23: =B25 | C23: =C25 | D23: =D25 | E23: =E25 | F23: =F25 | G23: =G25 | H23: =H25 | I23: =I25 | ... P23: =P25
A24: SALDO ANTERIOR | B24: 4607.91 | C24: =B25 | D24: =C25 | E24: =D25 | F24: =E25 | G24: =F25 | H24: =G25 | I24: =H25 | J24: =I25 | ... P24: =O25
A25: SALDO ATUAL | B25: 4607.91 | C25: 4607.91 | D25: 4607.91 | E25: 4607.91 | F25: 4607.91 | G25: 4607.91 | H25: =H24+250.62 | I25: =I24+359.99 | J25: =J24+359.99 | K25: =K24+420.47 | L25: 6358.97 | M25: 6358.97 | N25: 6358.97 | O25: 6358.97
A27: FUNDO DE RESERVA | B27: =B29 | C27: =C29 | D27: =D29 | E27: =E29 | F27: =F29 | G27: =G29 | H27: =H29 | I27: =I29 | ... P27: =P29
A28: SALDO ANTERIOR | B28: 3187.37 | C28: =B29 | D28: =C29 | E28: =D29 | F28: =E29 | G28: =F29 | H28: =G29 | I28: =H29 | J28: =I29 | ... P28: =O29
A29: SALDO ATUAL | B29: 3187.37 | C29: 3187.37 | D29: 3187.37 | E29: 3187.37 | F29: 3187.37 | G29: 3187.37 | H29: =H28+221.96 | I29: =I28+271.46 | J29: =J28+271.46 | K29: =K28+298.94 | L29: 4522.65 | M29: 4522.65 | N29: 4522.65 | O29: 4522.65
A31: BRADESCO | B31: =B33 | C31: =C33 | D31: =D33 | E31: =E33 | F31: =F33 | G31: =G33 | H31: =H33 | I31: =I33 | ... P31: =P33
A32: SALDO ANTERIOR | B32: 387344.88 | C32: =B33 | D32: =C33 | E32: =D33 | F32: =E33 | G32: =F33 | H32: =G33 | I32: =H33 | J32: =I33 | ... P32: =O33
A33: SALDO ATUAL | B33: =287388.77+104679.76 | C33: =789533.59+105389.31 | D33: =106269.31+792207.28 | E33: =107071.05+794645.23 | F33: =293895.48+106515.83+149092.68+320488.47 | G33: =770280.53+109059.62 | H33: =756023.73+109962.92 | I33: =111152.93+747245.89 | J33: =750500.62+112132.65 | K33: =113169.34+753671.39 | L33: =114355.56+114215.61+317027.13+325491.82 | M33: =112700.34+312789.43+179220.95+330589.66 | N33: =244080.19+112128.91+335000+316000 | O33: =114858.61+941415.06
A35: TOTAL | B35: =B5+B11+B17+B23+B27+B31 | C35: =C5+C11+C17+C23+C27+C31 | D35: =D5+D11+D17+D23+D27+D31 | E35: =E5+E11+E17+E23+E27+E31 | F35: =F5+F11+F17+F23+F27+F31 | G35: =G5+G11+G17+G23+G27+G31 | H35: =H5+H11+H17+H23+H27+H31 | I35: =I5+I11+I17+I23+I27+I31 | ... P35: =P5+P11+P17+P23+P27+P31
N37: 1770308.8

Sheet FOLHA
B1: MATHEUS | C1: MOISÉS
A2: INSS | B2: =1-C2 | C2: 0.3346
A3: FGTS | B3: =1-C3 | C3: 0.3539
A4: IRPF | B4: =1-C4 | C4: 0.1086

Sheet PF 22
D1: PLANILHA FINANCEIRA COND. DIAMOND TOWER 9155 - 2022
A2: PREVISÃO ORÇAMENTÁRIA - DIAMOND TOWER | B2: APROVADO 2022 | C2: JANEIRO | D2: FEVEREIRO | E2: MARÇO | F2: ABRIL | G2: MAIO | H2: JUNHO | I2: JULHO | J2: AGOSTO | K2: SETEMBRO | L2: OUTUBRO | M2: NOVEMBRO | N2: DEZEMBRO | O2: JANEIRO/23 | P2: FEVEIREIRO/23 | Q2: MARÇO/23 | S2: PREVISTO | T2: REALIZADO
A3: CONTRATOS MÃO DE OBRA | B3: =SUM(B4:B17) | C3: =SUM(C4:C17) | D3: =SUM(D4:D17) | E3: =SUM(E4:E17) | F3: =SUM(F4:F17) | G3: =SUM(G4:G17) | H3: =SUM(H4:H17) | I3: =SUM(I4:I17) | ... Q3: =SUM(Q4:Q17) | S3: =SUM(S4:S17) | T3: =SUM(T4:T17)
A4: Monitoramento - 01 Posto 24h - Central de Segurança - ONX | B4: 79000 | C4: =66360+5.5+3225.32+1548.13+575.13+447.11+208.06+77.29+8690+203.23+47.29+17.57+3950+813.84+3648.33 | D4: =66360+24996.22+11997.98+11997.98+4457.29+36106.55+26645.2+189.01+87.95+ 32.67+8690+3950 | E4: =66360+5.9+681.62+681.62+1464.81+253.22+2051.26+1513.75 | F4: =66360+5.9+8690+8690+3950 | G4: =66360+8690+3950 | H4: =6636+59724+8690 | I4: =66360+8690+3950+3950 | J4: =66360+8690+3950 | K4: =66360+8690+3950 | L4: =66360+8690+3950 | M4: =3950+66360+2.49+3950 | N4: =69420.96+2.49+4132.2 | O4: =72831.36+4335.2 | P4: =69849.7+4157.72 | Q4: =84035.28 | S4: =B4*15 | T4: =SUM(C4:Q10)
A5: Ronda Vigilante - 01 Posto 24h - ONX
A6: Porteiro 02 postos 8h - (Seg à Dom - das 7h as 22h) - ONX
A7: Expedição 01 posto 8h - (Seg à Sáb - das 08h às 16h20) - ONX
A8: Recepção - 04 postos 8h (das 7h as 22h) - ONX
A9: Limpeza - 03 Postos 44h semanais - ONX
A10: Serviços Gerais – 01 posto 44h semanais - ONX
A11: Oficial Manutenção - 01 Posto 44h semanais - R$1.887,00 | B11: 4147.23 | C11: =2540+5.5+313.24+101.05+296.4+107.78+1568.67+19.8 | D11: =1865.96+9.9+440.65+448+18.24+145.92 | E11: =1718.18+172.99+839.32+381.9+440+21.62+9.9 | F11: =160+691.82+440+440.65+20+1718.18+9.9 | G11: =160+691.82+440.65+20+440+2829.32+9.9 | H11: =269.21+103.05+1204.56+440.65+33.65+440+2576.35+19.8 | I11: =242.68+64.24+440.65+1391.57+30.33+444+2747.69+9.9 | J11: =440+440.65+74.59+2239.95+9.9 | K11: =440.65+68.88+440+551.08+2256.67+9.9 | L11: =241.26+78.49+440+2358.36+9.9+(0.3539*611.98) | M11: =1401.76+5.9+(0.1086*374.18)+(0.3346*2744.14)+440.65+440+422.4+2.49 | N11: =2341+983.45+39.49+(1681.84*0.3346)+3437.22+134.4+2.49 | O11: =2761+(900.36*0.3539)+182+39.49+(137.84/2)+364.8+2.49 | P11: =815+(613.06*0.3539)+(882/2)+39.49+(596.82*0.1086)+452.99 | Q11: =2384+(718.82*0.3539) | S11: =B11*15 | T11: =SUM(C11:Q11)
A12: Auxiliar Administração - Auxiliadora Predial | B12: 3600 | C12: =3600 | D12: =3600 | E12: 3600 | F12: 3600 | G12: 3600 | H12: 3600 | I12: 3600 | J12: 3600 | K12: 3600 | L12: =72.54+84+100.08+3600 | M12: =179.33+320+57.49+53.82+1936+49+273 | N12: =13.31+(1090-682.5)+245.01+1365 | O12: =66.57+245.01+1090+1365-682.5 | P12: =66.57+1090-682.5+245.01+1365 | S12: =B12*15 | T12: =SUM(C12:Q12)
A13: Gestão Total - Auxiliadora Predial | B13: 18500 | C13: =860.25+2035+14864.75+740 | D13: =14864.75+860.25+2035+740 | E13: =860.25+2035+14864.75+740 | F13: =2035+860.25+14864.75+740 | G13: =860.25+14864.75+2035+740 | H13: =860.25+15604.75+2035+740 | I13: =860.25+2035+15604.75 | J13: =860.25+2035+9700.25 | K13: =534.75+1265+9700.25 | L13: 11500 | M13: =10670.27+179.33+534.75+1265 | S13: =B13*15 | T13: =SUM(C13:Q13)
A14: Gestor Condominial - 01 Posto 44h semanais | H14: 440 | I14: =444 | J14: =3629.05+9.9+596.74+321.6+440+165 | K14: =3607.04+9.9+2482.57+440+263.43 | L14: =4099.9+9.9+(2790.43*0.6654)+(407.96*0.8914)+440+(0.6461*611.98) | M14: =3961.08+9.9+(0.6461*603.23)+1127.91+9.9+(0.8914*374.18)+(0.6654*2744.14)+440 | N14: =3967+858.12+2.49+39.49+(1681.84*0.6654) | O14: =4673+(900.36*0.6461)+400+39.49+(137.84/2) | P14: =3637+2.49+(613.06*0.6461)+1001+(882/2)+39.49+(596.82*0.8914) | Q14: =3933+(716.82*0.6461) | T14: =SUM(C14:Q14)
A15: Taxa Administração - Multiplan | B15: 0 | S15: =B15*15 | T15: =SUM(C15:Q15)
A16: Remuneração Subsíndico | B16: 6527 | C16: 42581.19 | D16: =29592.7+5.9 | E16: =5222.24+5.9 | F16: =5222.24+5.9 | G16: 5222.24 | H16: =5222.24+5.9 | I16: =5222.24+11.8 | J16: =5222.24 | K16: =5222.24+5.9 | L16: =5222.24 | M16: =5222.24+5.9 | N16: =5222.24+2.49 | O16: =5222.24 | P16: =5222.24+2.49 | Q16: =5222.24 | S16: =B16*15 | T16: =SUM(C16:Q16)
A17: Auditoria Externa | B17: 1000 | C17: 1000 | D17: 1000 | E17: 1100 | G17: =1100+5.9+1100 | H17: 1100 | I17: =1100 | J17: =1078+17.7 | K17: =22+1078+5.9 | L17: =1078+22 | M17: =22+1078+22 | N17: =22+1078+2.49 | O17: =22+1078 | P17: =22+1078+2.49 | S17: =B17*15 | T17: =SUM(C17:Q17)
A19: MANUTENÇÕES/LOCAÇÕES - CONTRATOS | B19: =SUM(B20:B29) | C19: =SUM(C20:C29) | D19: =SUM(D20:D29) | E19: =SUM(E20:E29) | F19: =SUM(F20:F29) | G19: =SUM(G20:G29) | H19: =SUM(H20:H29) | I19: =SUM(I20:I29) | ... Q19: =SUM(Q20:Q29) | S19: =SUM(S20:S29) | T19: =SUM(T20:T29)
A20: Central de Automação | B20: 0 | C20: =781.11+36.89 | D20: =781.35+36.65 | S20: =B20*15 | T20: =SUM(C20:Q20)
A21: Controle Pragas e Limpeza Caixa D'água (2x ano) | B21: 0 | S21: =B21*15 | T21: =SUM(C21:Q21)
A22: Limpeza Espelho D'água, Química e AFT com Material | B22: 800.01 | C22: =788+14.75 | D22: =780.75+12 | E22: =19.25+294 | F22: =6+270.75+515+11.8 | G22: =14.25+786.25 | H22: =13.75+130+794 | I22: =6+789.5 | J22: =10.5+783.25 | K22: =794.5+6.75 | L22: =5.5+788.25 | M22: =253.71+11.75+794+75.4+113.93 | N22: =6+789.5 | O22: =10.5+793.5 | P22: =6.5+2.7+795 | S22: =B22*15 | T22: =SUM(C22:Q22)
A23: Locação Impressora | B23: 206.76 | C23: 206.76 | D23: 206.76 | E23: 206.76 | F23: 206.76 | H23: 206.76 | I23: 206.76 | J23: =206.76 | K23: =206.76 | L23: =206.76 | M23: =206.76 | O23: =206.76 | P23: =206.76 | Q23: =223.82 | S23: =B23*15 | T23: =SUM(C23:Q23)
A24: Locação Rádios Comunicadores (9) | B24: 0 | C24: 480 | D24: 480 | E24: 480 | S24: =B24*15 | T24: =SUM(C24:Q24)
A25: Manutenção ar condicionado / exaustão áreas comuns | B25: 3152.21 | C25: =146.58+3004.5 | D25: =146.52 | E25: =3004.5+146.52+3004.5 | F25: =146.52 | G25: =3004.5+3004.5 | H25: =146.52+146.52+3004.5 | I25: =146.52 | J25: =2846.96+5.9+157.55+2846.95 | K25: =146.52+146.52+157.55+2846.95 | L25: =146.52+157.55+2846.95 | M25: =146.52+157.55+2846.95+157.55 | N25: =146.52 | O25: =2846.95+157.55+146.52+3016.9 | P25: =1096.53+166.96+504.15+155.27 | Q25: =3016.9 | S25: =B25*15 | T25: =SUM(C25:Q25)
A26: Manutenção CFTV/Controle de Acesso/Central Alarme | B26: 3320 | C26: =3227.37+92.63 | D26: =3227.37+92.63 | E26: =3227.37+92.63 | F26: =3227.37 | G26: =3227.37+11.8+92.63 | H26: =3227.27+11.8+92.63 | I26: =3227.37+92.63 | J26: =3227.37+92.63 | K26: =3227.37+92.63 | L26: =3227.37+92.63 | M26: =3227.37+92.63+92.63 | N26: =3227.37+92.63 | O26: =3227.37+92.63 | P26: =3227.37+92.63 | Q26: =3437.79 | S26: =B26*15 | T26: =SUM(C26:Q26)
A27: Manutenção Preventiva Elevadores (7) - Com Peças - Atlas | B27: 8300 | C27: =3174.9+175.7+7499.05 | D27: =11822.82+163.4+385.95+415 | E27: =7499.05+415+8511.98 | F27: =385.95+438.08+471.06+24.51+694.87+7499.05 | G27: =385.95+49.95+415+7499.05 | H27: =46.46+385.95+22.79+415+21.82+7499.05 | I27: =385.95+415+7499.05 | J27: =385.95+415+7499.05 | K27: =385.95+415+7499.03 | L27: =385.95+415+7499.03 | M27: =385.95+415+7499.03+415 | N27: =415+385.95+7499.05 | O27: =415+385.95+7950.13 | P27: =439.98+409.18+7950.43 | S27: =B27*15 | T27: =SUM(C27:Q27)
A28: Limpeza da Fachada | B28: 6000 | C28: =660+5130+210 | D28: =660+210 | E28: =5130+5.9+660+210+5130 | F28: =660+210 | G28: =5130+660+210+5130+5.9 | H28: =660+210+5130+5.9 | I28: =660+210+5130+11.8 | J28: =660+210+5130 | K28: =660+210 | L28: =5130+11.8 | M28: =660+210+210+5130+2.49 | N28: =5130+2.49 | O28: =210+5100 | P28: =210 | Q28: =5130 | S28: =B28*15 | T28: =SUM(C28:Q28)
A29: Manutenção preventiva motor gerador | B29: 1173.12 | C29: =968.1+61+201.63 | D29: =56.73+968.1+136.41+61 | E29: =56.73+968.1+61+139.07 | F29: =968.1+134.2+56.73+61 | G29: =56.73+968.1+134.2+61 | H29: =968.1+56.73+134.2+61 | I29: =118.85+56.73+134.2+61+968.1 | J29: =56.73+968.1+134.2+61 | K29: =968.1+56.73+134.2+61 | L29: =968.1+56.73+134.2+61 | M29: =1047.97+56.73+145.27+66.03+66.03 | N29: =1047.97+66.03 | O29: =1047.97+66.03+61.41 | P29: =66.03+61.41+1047.97 | S29: =B29*15 | T29: =SUM(C29:Q29)
A31: MANUTENÇÕES - SEM CONTRATO | B31: =SUM(B32:B39) | C31: =SUM(C32:C39) | D31: =SUM(D32:D39) | E31: =SUM(E32:E39) | F31: =SUM(F32:F39) | G31: =SUM(G32:G39) | H31: =SUM(H32:H39) | I31: =SUM(I32:I39) | ... Q31: =SUM(Q32:Q39) | S31: =SUM(S32:S39) | T31: =SUM(T32:T39)
A32: Lixo/Entulho/Manutenção Externa - Despesa Compartilhada | B32: 3000 | C32: 1009.9 | D32: =626.44+784.98+1105.99 | F32: =656.82 | G32: =656.82 | J32: =3732.09+1592.24 | L32: =750.45 | M32: =1333.7 | N32: =1059.99+1469.44 | P32: =1288.65 | S32: =B32*15 | T32: =SUM(C32:Q32)
A33: Manutenção Bombas de Recalque | B33: 120 | E33: =340+5.9 | H33: 823.33 | O33: =180 | S33: =B33*15 | T33: =SUM(C33:Q33)
A34: Manutenção Interfones | B34: 50 | E34: =290+5.9 | O34: =366.34 | P34: =366.33 | S34: =B34*15 | T34: =SUM(C34:Q34)
A35: Manutenção Predial | B35: 3000 | C35: =2089.22+325.6+364.08+2555.96+11+118.4+4515+3120 | D35: =42.96+133.18+3120+4515+760+340+11.8+114.56 | E35: =1595+1885+5.9+3505.49 | G35: =3965+5.9+823.33 | H35: =156.86+345.25+667.5+5.9+45+393.25+727.5+5.9 | L35: =2165 | N35: =956.6+2.49 | O35: =151.2+2.49+9+634.7+956.6+2.49 | P35: =956.6+2.49 | S35: =B35*15 | T35: =SUM(C35:Q35)
A36: Manutenção Preventiva Sistema de Incêndio | B36: 200 | E36: =12500+5.9 | F36: =10000 | L36: =967.86+88.78+1518.63+967.85+883.96+5.9+5.9 | M36: =967.85+2500 | P36: =471.98 | S36: =B36*15 | T36: =SUM(C36:Q36)
A37: Obrigações Legais (AFT, certificado de qualidade do ar de ambiente climatizado, certificado digital, inspeção da esccada pressurizada, laudo de potabilidade, teste mangueiras, recarga extintores, SPDA, subestação de energia) | B37: 2100 | G37: =6945+5.9 | H37: =1050.21+1466.96+193.6+193.6 | I37: =17.6+81.84+88.78 | J37: =88.78+271.05+3091.9 | K37: =13.95+15+63.1 | L37: =132.3+180+5.9 | M37: =132.3+2.7+270+2.7 | P37: =298.16 | Q37: =1200 | S37: =B37*15 | T37: =SUM(C37:Q37)
A38: Controle Pragas e Limpeza Caixa D'água (2x ano) | B38: 300 | C38: =503.38+27.75+65.65 | D38: =503.38+27.75+66.72 | E38: =535.33+29.51+27.75+69.81 | I38: =404.88+17.6+81.84+52.8 | J38: =22.32 | N38: =2208.78 | O38: =123.23+26.5 | S38: =B38*15 | T38: =SUM(C38:Q38)
A39: Paisagismo interno | B39: 100 | S39: =B39*15 | T39: =SUM(C39:Q39)
A41: MATERIAIS E EQUIPAMENTOS | B41: =SUM(B42:B54) | C41: =SUM(C42:C54) | D41: =SUM(D42:D54) | E41: =SUM(E42:E54) | F41: =SUM(F42:F54) | G41: =SUM(G42:G54) | H41: =SUM(H42:H54) | I41: =SUM(I42:I54) | ... Q41: =SUM(Q42:Q54) | S41: =SUM(S42:S54) | T41: =SUM(T42:T54)
A42: Cartões para controle de acesso | B42: 100 | J42: =281.4+393.5 | K42: =315+647.32 | M42: -939 | N42: =371 | S42: =B42*15 | T42: =SUM(C42:Q42)
A43: Chaveiro | B43: 20 | C43: =56+5.5 | I43: =50+5.9 | S43: =B43*15 | T43: =SUM(C43:Q43)
A44: Lâmpadas | B44: 500 | E44: 646.5 | F44: =158+350+460+5.9 | G44: =302.4+555.42+680+960+1050+17.7+261.91 | I44: 489.5 | J44: =489.5 | K44: =54.95+455.2+5.9 | S44: =B44*15 | T44: =SUM(C44:Q44)
A45: Materiais/Serviços Obras Diversas (Alvenaria, Serralheria, Funilaria, Outros) | B45: 400 | C45: =196.6 | D45: 242.7 | E45: =71.2+13.5+445+345.25 | F45: =492.5+305.3+322.5 | G45: =238.5+105.64+180.95+837.05 | H45: =989.9+483.7+41+560.8+33 | I45: =240.01+152.7 | J45: =126.2+175 | K45: =186.55+226.2+194.9 | L45: =49.39+288.2 | N45: =179.75 | O45: =20.95+10 | S45: =B45*15 | T45: =SUM(C45:Q45)
A46: Material de Ferragem (Elétrica, Hidráulica e Ferramentas) | B46: 600 | C46: =33.05+167.2+1359.83 | D46: =89.8+89.55+ 127.05+407.1+607+48.15+31.35+5.9 | E46: =80.5+123.55+760+5.9+274.8 | F46: =984.5+29.7+844.05+54.35+760+17.7 | G46: =72+429.9+11.8+15+676.8+135+308.1+420.31+533.95+403.37 | H46: =72.3+99.8+124.59+231.85+453.25+174.9+32.6+320.9+1015.55+420+87.7+52.8+379.8 | I46: =199.9+238.15+269.5+68+145+5.9+424.95+472.75+229.9+219 | J46: =55 | K46: =53.7+38.18+199.5+5.9+111.8+198+66.95 | L46: =252.65 | M46: =56.65+65+16.25+252.95+216.15+69.75+61.7 | N46: =129.5+110.95+50.6+65.25+158.01+427.22 | O46: =69.95+242.25+159.9+43.34 | P46: =90.5+196+320.2 | Q46: =298.45+93.45 | S46: =B46*15 | T46: =SUM(C46:Q46)
A47: Material Expediente Interno | B47: 300 | C47: =145.5+100.08 | D47: 100.08 | E47: 207.64 | G47: =215.73+100.08 | H47: =385.65+374.72+5.9 | I47: =89.99+50+275.98+104+36.9 | J47: =199.02+100.08 | K47: =226.53+100.08 | L47: =239.9+29.9+54.8 | M47: =82.23 | O47: =343.2 | S47: =B47*15 | T47: =SUM(C47:Q47)
A48: Material Limpeza/Consumíveis | B48: 1500 | C48: 793.26 | D48: 399.38 | E48: =598.59+ 391.1+522.62 | F48: =400.06+1048.72 | G48: =337.92+593.4+1155.08+36 | H48: =139.9+1667.43+741.75+5.9+803.3+881.32 | I48: =620.23+242.04 | J48: =922.55+270.44+869.05 | K48: =280.84+1216.86 | L48: =1496.99+244.27+315+149.52 | M48: =1722.08 | N48: =342.56+316.46+269.63+251.67 | O48: =847.3+343.2+186.67+879.93 | P48: =323.55+529.46 | S48: =B48*15 | T48: =SUM(C48:Q48)
A49: Peças elevador | B49: 1100 | D49: =77.7+765.14+42.34 | E49: 39.38 | G49: =467.38+902.68 | H49: 394.36 | I49: =20.3+41.05+741.84 | J49: =38.18+41.05+741.84 | K49: =38.18 | S49: =B49*15 | T49: =SUM(C49:Q49)
A50: Móveis e Utensílios | B50: 500 | C50: 1044.14 | D50: =5.9+1681+5.9+1044.14 | E50: =1044.14+402 | F50: =1044.14 | G50: 1044.14 | H50: =779.9+11.8+3849+289.99 | I50: =266.68+823.04 | J50: =266.66 | K50: =266.66+184.45 | L50: =113.9+2.49 | N50: =498 | P50: =2254 | S50: =B50*15 | T50: =SUM(C50:Q50)
A51: Peças Ar Condicionado/Exaustores | B51: 900 | P51: =404.66+280 | S51: =B51*15 | T51: =SUM(C51:Q51)
A52: Peças de reposição para extintores e hidrantes e recargas eventuais | B52: 50 | F52: =1500+5.9 | S52: =B52*15 | T52: =SUM(C52:Q52)
A53: Peças para Grupo Gerador, limpeza semestral filtro e óleo e óleo diesel | B53: 270 | J53: =362.5 | P53: =912.5 | S53: =B53*15 | T53: =SUM(C53:Q53)
A54: Peças para manutenção das catracas | B54: 180 | M54: =60 | S54: =B54*15 | T54: =SUM(C54:Q54)
A56: DESPESAS ADMINISTRATIVAS | B56: =SUM(B57:B63) | C56: =SUM(C57:C63) | D56: =SUM(D57:D63) | E56: =SUM(E57:E63) | F56: =SUM(F57:F63) | G56: =SUM(G57:G63) | H56: =SUM(H57:H63) | I56: =SUM(I57:I63) | ... Q56: =SUM(Q57:Q63) | S56: =SUM(S57:S63) | T56: =SUM(T57:T63)
A57: Telefonia/Internet- apenas telefone, internet comodato | B57: 108.48 | C57: =23.99+279.65 | D57: =23.99+86.66 | E57: =22.31+135.64 | F57: =24.68+139.36 | G57: =24.67+36.58 | H57: =24.67 | I57: =24.67+39.9 | J57: =59.85 | K57: =49.44 | L57: =57.05 | M57: =50.44 | N57: =53.03 | O57: =58.87 | P57: =55.59 | S57: =B57*15 | T57: =SUM(C57:Q57)
A58: Impressões/Cópias | B58: 70 | C58: =135.32+105+5.5 | D58: 195.52 | E58: 53.62 | F58: 56.63 | G58: =309.9 | H58: 70.39 | I58: 72.97 | J58: =70.82 | K58: =73.83 | S58: =B58*15 | T58: =SUM(C58:Q58)
A59: Correio/Remessa Correspondências/Motoboy/Diversas | B59: 260 | C59: =20.54+82.05+27.35 | E59: 17.7 | F59: 30.81 | H59: 67.44 | J59: =20.54 | L59: =22.84+108.51+22.84+5.9+5.9 | N59: =43.52+29.92+32.92 | O59: =277.5 | P59: =128.84+2.49 | Q59: =226.21 | S59: =B59*15 | T59: =SUM(C59:Q59)
A60: Impostos - DIRF/DARF/ISSQN/PIS/COFINS | B60: 100 | C60: 42 | D60: 42 | E60: 42 | F60: 42 | G60: 42 | H60: 42 | I60: 84 | J60: =3037.26+2702.99+84 | K60: =84 | N60: =5213.59+9207.05+604.2+0.03+338.09+376.03+55.8+75.52+12709.04 | O60: =19.78+26.99+24.37+117.28+70.93+55.8+15870.69+218.33 | P60: =55.8+14537.03+76.63+191.58 | S60: =B60*15 | T60: =SUM(C60:Q60)
A61: Material Expediente APL | B61: 100 | C61: =172.51+410.97 | E61: 100.08 | F61: 100.08 | H61: 100.08 | I61: 100.08 | N61: 23.29 | S61: =B61*15 | T61: =SUM(C61:Q61)
A62: Taxa Desepesas com Assembleia | B62: 50 | D62: 258.1 | H62: 235.85 | N62: 360 | S62: =B62*15 | T62: =SUM(C62:Q62)
A63: Custas Judiciais | B63: 100 | S63: =B63*15 | T63: =SUM(C63:Q63)
A65: COTA | B65: =SUM(B3,B19,B31,B41,B56) | C65: =SUM(C3,C19,C31,C41,C56) | D65: =SUM(D3,D19,D31,D41,D56) | E65: =SUM(E3,E19,E31,E41,E56) | F65: =SUM(F3,F19,F31,F41,F56) | G65: =SUM(G3,G19,G31,G41,G56) | H65: =SUM(H3,H19,H31,H41,H56) | I65: =SUM(I3,I19,I31,I41,I56) | ... Q65: =SUM(Q3,Q19,Q31,Q41,Q56) | S65: =SUM(S3,S19,S31,S41,S56) | T65: =SUM(T3,T19,T31,T41,T56)
A67: DESPESAS VARIÁVEIS | B67: =SUM(B68:B70) | C67: =SUM(C68:C70) | D67: =SUM(D68:D70) | E67: =SUM(E68:E70) | F67: =SUM(F68:F70) | G67: =SUM(G68:G70) | H67: =SUM(H68:H70) | I67: =SUM(I68:I70) | ... Q67: =SUM(Q68:Q70) | S67: =SUM(S68:S70) | T67: =SUM(T68:T70)
A68: Água e Esgoto - Área Comum | B68: - | C68: 8039.3 | D68: 8039.3 | E68: 8039.3 | F68: 8039.3 | G68: =8039.3 | H68: 8039.3 | I68: 8039.3 | J68: =8039.3 | K68: 8039.3 | L68: =8039.3 | M68: =9100.72 | N68: =12379.17 | O68: 9100.72 | P68: =10633.73 | T68: =SUM(C68:Q68)
A69: Energia Elétrica - Área Comum | B69: - | C69: 33316.03 | D69: 33993.82 | E69: 28198.36 | F69: 31315.78 | G69: 25533.33 | H69: 22803.23 | I69: 19739.97 | J69: 19690.48 | K69: 20057.75 | L69: =18325.29 | M69: =18573.55 | N69: 19116.52 | O69: =21403.23 | Q69: 22347.4 | T69: =SUM(C69:Q69)
A70: Seguro fogo | B70: - | J70: =6690.63 | L70: =6690.63-3895.02 | M70: =6690.63 | N70: =6690.63 | T70: =SUM(C70:Q70)
A72: OUTRAS DESPESAS | B72: =SUM(B73:B76) | C72: =SUM(C73:C76) | D72: =SUM(D73:D76) | E72: =SUM(E73:E76) | F72: =SUM(F73:F76) | G72: =SUM(G73:G76) | H72: =SUM(H73:H76) | I72: =SUM(I73:I76) | ... Q72: =SUM(Q73:Q76) | S72: =SUM(S73:S76) | T72: =SUM(T73:T76)
A73: Despesas Não Orçadas | B73: - | C73: =0.66+2573.31+11+8.9+440+1492.5+440+9.9+632.5+995+422.4 | D73: =5.9+980+10668.47+632.5+995+415+165 | E73: =29.46+901.81 | F73: =47.03+31.38+103.5+445+345.25+39.99+39.92+92.63+393.25 | G73: =206.76+478.5+39.98+199+1500+5.9+445+345.25+393.25+1170+1170+44.92 | H73: =39.91+39.94+39.98+50.56+39.96+45+36.96+104.5 | I73: =1543+32.45+2064+41.08+51.35+20.54+20.54+5.9+393.25+34.92+34.92+5.9+22.5+1543+823.34 | J73: =5.9+421.11+1543+143.43+23.9+117.5 | K73: =39.96+39.03+210+5.9+150+2645.73+17.7+27.5+5.9+47.05+12.5+5.9 | L73: =199.5+53.16+1425+1028+129.84+19.09+6.88+9.54+39+39+64.92 | M73: =2375.01+264.57+2.49+240+54.31+2.49+32.63 | N73: =72.9+2.49+160.05 | O73: =145.8 | P73: =388.84 | Q73: =72.9 | T73: =SUM(C73:Q73)
A74: Despesas reembolsáveis | B74: - | C74: =175.51+150.98+1023 | D74: =180.3+155.1 | E74: =180.7+210.07 | F74: =176.5+151.83 | G74: =350+881+176.64+151.95 | H74: =188.42+2800+162.08 | I74: =622.5+177.28+6690.63+129.84+19.09+6.88+9.54 | J74: =129.84+19.09+6.88+9.54+64.92+350+32.45+179.35 | L74: =910.8+20+3749.06+969.26+90+165.99+342.13+124.91+230.34+232.08+3895.02+554+26.99+20.83+54.27+2.51+2.98+3.57+3.55+11.63+3.71+3.38+554+50+840+327.6+5.9+29.5+17.7 | M74: =110+42.9+50+19.5+18.59+19.78+24.37+26.99+3.4+7.02+2.56+4.72+4.76+3749.06+1322.34+1193.98+487.2+2.49+18.59+19.78+24.37+22.46+50+19.5+26.99 | N74: =24.37+29+1322.34+969.26+70+2.49+2.49+2.49+1193.98+1196.22+1926.1+2.49+2.49+2.49 | O74: =3749.06+1926.1+39.31+39.31+39.19+100.5+39.19+969.26+1193.98+1322.34+103.31 | P74: =4846.46+1322.34+193.11+2.49+2.49+2.49+2.49+1926.22+1926.1+2.49+2.49+2.49+20 | Q74: =969.26 | T74: =SUM(C74:Q74)
A75: Honorários advocatícios | J75: =3749.06+5.9+3749.06+5.9+1322.34+761.17+11.8+279.1+200.31+123.88+299.56+146.96+304.42+135.23+112.1+153.95 | N75: =1910.81+2.49+3919.6+4899.5+1080+2.49+2.49+2.49 | O75: =1910.81+80.4 | P75: =1910.81+2.49+39.19 | Q75: =1911 | T75: =SUM(C75:Q75)
A76: Transferências Entre Contas | B76: - | C76: =12149.55+6000 | D76: =316207.13+11.8 | H76: 1500 | T76: =SUM(C76:Q76)
A78: TOTAL DESPESAS CONTA PRINCIPAL | B78: =B72+B67+B65 | C78: =C72+C67+C65 | D78: =D72+D67+D65 | E78: =E72+E67+E65 | F78: =F72+F67+F65 | G78: =G72+G67+G65 | H78: =H72+H67+H65 | I78: =I72+I67+I65 | ... N78: =N72+N67+N65 | O78: =O65+O67+O72 | P78: =P65+P67+P72 | Q78: =Q72+Q67+Q65 | S78: =S72+S67+S65 | T78: =T72+T67+T65

Sheet -
A1: HISTÓRICO DE INADIMPLÊNCIA EDIFÍCIO DIAMOND TOWER - JANEIRO/22 - FEVEREIRO/23
B2: 2022 | N2: 2023
B3: JANEIRO | C3: FEVEREIRO | D3: MARÇO | E3: ABRIL | F3: MAIO | G3: JUNHO | H3: JULHO | I3: AGOSTO | J3: SETEMBRO | K3: OUTUBRO | L3: NOVEMBRO | M3: DEZEMBRO | N3: JANEIRO | O3: FEVEREIRO
A4: VALOR BASE | B4: 444638.41 | C4: 452519.74 | D4: 477047.67 | E4: 469964.99 | F4: 482474.11 | G4: 390770.2 | H4: 334394.64 | I4: 325979.62 | J4: 218963.41 | K4: 123518.56 | L4: 177425.99 | M4: 177425.99 | N4: 177425.99 | O4: 177425.99
A5: VALOR CORRIGIDO | B5: 902847.58 | C5: 932606.15 | D5: 979124.08 | E5: 992506.65 | F5: 1012335 | G5: 778609.98 | H5: 698309.47 | I5: 687678.86 | J5: 495200.69 | K5: 263351 | L5: 260104.22 | M5: 260104.22 | N5: 260104.22 | O5: 260104.22
E50: jan 22 | H50: abril 22 | K50: jul 22 | N50: ago 22
E51: valor base | F51: 444638.41 | H51: valor base | I51: 469694.99 | K51: valor base | L51: 334394.64 | N51: valor base | O51: 325979.62
E52: multa | F52: 8892.82 | H52: multa | I52: 9393.98 | K52: multa | L52: 6687.79 | N52: multa | O52: 6583.89
E53: juros | F53: 236345.32 | H53: juros | I53: 266619.5 | K53: juros | L53: 190416.14 | N53: juros | O53: 192004.56
E54: correção | F54: 212971.03 | H54: correção | I54: 246798.08 | K54: correção | L54: 166810.9 | N54: correção | O54: 163110.79
E55: valor corrigido | F55: =SUM(F51:F54) | H55: valor corrigido | I55: 992506.65 | K55: valor corrigido | L55: =SUM(L51:L54) | N55: valor corrigido | O55: =SUM(O51:O54)
E56: NOV 22 | H56: marco 22 | K56: jun 22 | N56: set 22
E57: valor base | F57: 177425.99 | H57: valor base | I57: 477047.67 | K57: valor base | L57: 390770.2 | N57: valor base | O57: 218963.41
E58: multa | F58: 4379.39 | H58: multa | I58: 9541.04 | K58: multa | L58: 7815.47 | N58: multa | O58: 4379.39
E59: juros | F59: 151595.55 | H59: juros | I59: 255531.31 | K59: juros | L59: 201248.3 | N59: juros | O59: 151595.55
E60: correção | F60: 120262.34 | H60: correção | I60: 237004.06 | K60: correção | L60: 178776.01 | N60: correção | O60: 120262.34
E61: valor corrigido | F61: =260104.22 | H61: valor corrigido | I61: =SUM(I57:I60) | K61: valor corrigido | L61: =SUM(L57:L60) | N61: valor corrigido | O61: =SUM(O57:O60)
E62: DEZ 22 | H62: fev 22 | K62: maio 22 | N62: out 22
E63: valor base | F63: 177425.99 | H63: valor base | I63: 452519.74 | K63: valor base | L63: 482474.11 | N63: valor base | O63: 123518.56
E64: multa | F64: 4379.39 | H64: multa | I64: 9050.38 | K64: multa | L64: 9649.58 | N64: multa | O64: 2470.47
E65: juros | F65: 151595.55 | H65: juros | I65: 245910.62 | K65: juros | L65: 274101.69 | N65: juros | O65: 76946.1
E66: correção | F66: 120262.34 | H66: correção | I66: 225125.41 | K66: correção | L66: 246109.61 | N66: correção | O66: 60415.87
E67: valor corrigido | F67: =260104.22 | H67: valor corrigido | I67: =SUM(I63:I66) | K67: valor corrigido | L67: =SUM(L63:L66) | N67: valor corrigido | O67: =SUM(O63:O66)
E68: JAN 23
E69: valor base | F69: 177425.99
E70: multa | F70: 4379.39
E71: juros | F71: 151595.55
E72: correção | F72: 120262.34
E73: valor corrigido | F73: =260104.22
E74: FEV 23
E75: valor base | F75: 177425.99
E76: multa | F76: 4379.39
E77: juros | F77: 151595.55
E78: correção | F78: 120262.34
E79: valor corrigido | F79: =260104.22

Sheet ESTUDO
C3: ANO | D3: 2023 | F3: 2024 | H3: 2025
C4: CONTA | D4: MAR | E4: FEV | F4: MAR | G4: FEV | H4: MAR | I4: MOMENTO
C5: PRINCIPAL | D5: ='RS 2023'!C10 | E5: ='RS 2023'!N10 | F5: ='RS 2024'!C10 | G5: ='RS 2024'!N10 | H5: ='RS 2025'!C10 | I5: ='RS 2025'!H10
C6: SALA DE EVENTOS | D6: ='RS 2023'!C16 | E6: ='RS 2023'!N16 | F6: ='RS 2024'!C16 | G6: ='RS 2024'!N16 | H6: ='RS 2025'!C16 | I6: ='RS 2025'!H16
C7: ESTACIONAMENTO | D7: ='RS 2023'!C22 | E7: ='RS 2023'!N22 | F7: ='RS 2024'!C22 | G7: ='RS 2024'!N22 | H7: ='RS 2025'!C22 | I7: ='RS 2025'!H22
C8: INADIMPLÊNCIA | D8: ='RS 2023'!C26 | E8: ='RS 2023'!N26 | F8: ='RS 2024'!C26 | G8: ='RS 2024'!N26 | H8: ='RS 2025'!C26 | I8: ='RS 2025'!G26
C9: FUNDO RESERVAS | D9: ='RS 2023'!C30 | E9: ='RS 2023'!N30 | F9: ='RS 2024'!C30 | G9: ='RS 2024'!N30 | H9: ='RS 2025'!C30 | I9: ='RS 2025'!H26
C10: TOTAL | D10: =SUM(D5:D9) | E10: =SUM(E5:E9) | F10: =SUM(F5:F9) | G10: =SUM(G5:G9) | H10: =SUM(H5:H9) | I10: =SUM(I5:I9)

Sheet P.O 2019 3,77%
A2: PREVISÃO ORÇAMENTÁRIA 2018 - DIAMOND TOWER
A4: 2018 - Março/19 a Fev/20 | C4: 2018/2019 PO VIGENTE | E4: 2019/2020 PROPOSTA | G4: Mês de reajuste | H4: Valor em janeiro 2018 | I4: Indice de reajuste | J4: VALOR ATUAL CONTRATOS | K4: INDICE REAL | L4: VALOR ANUAL 2019/2020
A5: CONTRATOS MÃO DE OBRA | C5: =SUM(C6:C17) | E5: =SUM(E6:E17) | J5: =SUM(J6:J17) | K5: =E5/C5-1 | L5: =E5*12
A6: Monitoramento - 01 Posto 24h - Central de Segurança | C6: =17904.19+26040.69 | E6: =(J6)+(J6*I6) | G6: Dissídio - Janeiro | H6: =8755.05+7927.74 | I6: 0.05 | J6: =17153.24+24948.48 | K6: =E6/C6-1 | L6: =E6*12
A7: Ronda Vigilante - 01 Posto 24h | G7: Dissídio - Janeiro | H7: =11472.28+12791.95 | I7: 0.05
A8: Porteiro 02 postos 8h - (Seg à Dom - das 7h as 22h) | C8: =8462.3295835+4231.17+14665.28 | E8: =(J8)+(J8*I8) | G8: Dissídio - Janeiro | H8: 8039.76 | I8: 0.05 | J8: =8375.02+4187.52+14665.28 | K8: =E8/C8-1 | L8: =E8*12
A9: Expedição 01 posto 8h - (Seg à Sáb - das 08h às 16h20) | G9: Dissídio - Janeiro | H9: 4019.89 | I9: 0.05
A10: Recepção - 04 postos 8h (das 7h as 22h) | G10: Dissídio - Janeiro | H10: 14665.28 | I10: 0.05
A11: Limpeza - 03 Postos 44h semanais | C11: 12802.044 | E11: =(J11)+(J11*I11) | G11: Dissídio - Janeiro | H11: 12162.77 | I11: 0.05 | J11: 12669.96 | K11: =E11/C11-1 | L11: =E11*12
A12: Serviços Gerais – 01 posto 44h semanais | C12: 4756.3534 | E12: =(J12)+(J12*I12) | G12: Dissídio - Janeiro | H12: 4518.84 | I12: 0.05 | J12: 4707.28 | K12: =E12/C12-1 | L12: =E12*12
A13: Oficial Manutenção - 01 Posto 44h semanais | C13: 5283.33 | E13: =(J13)+(J13*I13) | G13: Dissídio - Janeiro | H13: 5019.51 | I13: 0.05 | J13: 5226.22 | K13: =E13/C13-1 | L13: =E13*12
A14: Auxiliar Administração - Auxiliadora Predial | C14: 3413.57 | E14: =(J14*6+J14*(I14+100%)*6)/12 | G14: IGPM - Setembro | H14: 3379.77 | I14: 0.0421 | J14: 3613.85 | K14: =E14/C14-1 | L14: =E14*12
A15: Gestão Total - Auxiliadora Predial - (2 Gestores) | C15: 18098.08 | E15: =(J15)+(J15*I15) | G15: Dissídio - Abril | H15: 17236.27 | I15: 0.05 | J15: 17505.16 | K15: =E15/C15-1 | L15: =E15*12
A16: Taxa Administração - Multiplan | C16: 1545 | E16: 1790.91 | G16: IGPDI - Setembro | H16: 1500 | I16: =K16 | J16: 1500 | K16: =E16/C16-1 | L16: =E16*12
A17: Auditoria Externa | C17: 1296.66 | E17: =(J17*7+J17*(I17+100%)*5)/12 | G17: IGPM - Outubro | H17: 1283.82 | I17: 0.0421 | J17: 1426.52 | K17: =E17/C17-1 | L17: =E17*12
A19: MANUTENÇÕES/LOCAÇÕES - CONTRATOS | B19: =#REF!/#REF! | C19: =SUM(C20:C28) | E19: =SUM(E20:E28) | J19: =SUM(J20:J28) | K19: =E19/C19-1 | L19: =E19*12
A20: Central de Automação | C20: 826.18 | E20: =(J20)+(J20*I20) | G20: IGPM - Março | H20: 818 | I20: 0.0421 | J20: 818 | K20: =E20/C20-1 | L20: =E20*12
A21: Controle Pragas e Limpeza Caixa D'água (2x ano) | C21: 568.63 | E21: =(J21*6+J21*(I21+100%)*6)/12 | G21: IGPM - Setembro | H21: 563 | I21: 0.0421 | J21: 563.4 | K21: =E21/C21-1 | L21: =E21*12
A22: Limpeza Espelho D'água, Química e AFT com Material (2x semana) | C22: 707 | E22: =(J22*8+J22*(I22+100%)*4)/12 | G22: IGPM - Novembro | H22: 700 | I22: 0.0421 | J22: 707 | K22: =E22/C22-1 | L22: =E22*12
A23: Locação Impressora | C23: 151.5 | E23: =(J23*6+J23*(I23+100%)*6)/12 | G23: IGPM - Setembro | H23: 150 | I23: 0.0421 | J23: 200 | K23: =E23/C23-1 | L23: =E23*12
A24: Locação Rádios Comunicadores (9) | C24: 484.8 | E24: =(J24*3+J24*(I24+100%)*9)/12 | G24: IGPM - Junho | H24: 480 | I24: 0.0421 | J24: 480 | K24: =E24/C24-1 | L24: =E24*12
A25: Manutenção ar condicionado / exaustão áreas comuns | C25: 2768.85 | E25: =(J25)+(J25*I25) | G25: INPC - Janeiro | H25: 2741.44 | I25: 0.0343 | J25: 2792.7 | K25: =E25/C25-1 | L25: =E25*12
A26: Manutenção CFTV/Controle de Acesso/Central Alarme | C26: 2727 | E26: =(J26*7+J26*(I26+100%)*5)/12 | G26: IGPM - Outubro | H26: 2700 | I26: 0.0421 | J26: 2700 | K26: =E26/C26-1 | L26: =E26*12
A27: Manutenção Preventiva Elevadores (7) - Com Peças - Atlas | C27: 11536 | E27: =(J27*6+J27*(I27+100%)*6)/12 | G27: IGPDI - Setembro | H27: 11200 | I27: 0.0452 | J27: 11200 | K27: =E27/C27-1 | L27: =E27*12
A28: Manutenção preventiva motor gerador | C28: 883.04 | E28: =(J28*7+J28*(I28+100%)*5)/12 | G28: IGPM - Outubro | H28: 874.29 | I28: 0.0421 | J28: 962.15 | K28: =E28/C28-1 | L28: =E28*12
A30: MANUTENÇÕES - SEM CONTRATO | B30: =#REF!/#REF! | C30: =SUM(C31:C37) | D30: =C30/#REF! | E30: =SUM(E31:E37) | K30: =E30/C30-1 | L30: =E30*12
A31: Lixo/Entulho/Manutenção Externa - Despesas Compartilhadas | C31: 3000 | E31: 3000 | K31: =E31/C31-1 | L31: =E31*12
A32: Manutenção Bombas de Recalque | C32: 120 | E32: 120 | K32: =E32/C32-1 | L32: =E32*12
A33: Manutenção Interfones | C33: 50 | E33: 50 | K33: =E33/C33-1 | L33: =E33*12
A34: Manutenção Predial | C34: 3000 | E34: 4000 | K34: =E34/C34-1 | L34: =E34*12
A35: Manutenção Preventiva Sistema de Incêndio | C35: 100 | E35: 100 | K35: =E35/C35-1 | L35: =E35*12
A36: Obrigações Legais (AFT, certificado de qualidade do ar de ambiente climatizado, certificado digital, inspeção da esccada pressurizada, laudo de potabilidade, teste mangueiras, recarga extintores, SPDA, subestação de energia) | C36: 3200 | E36: 3200 | K36: =E36/C36-1 | L36: =E36*12
A37: Paisagismo interno | C37: 100 | E37: 100 | K37: =E37/C37-1 | L37: =E37*12
A39: MATERIAIS E EQUIPAMENTOS | B39: =#REF!/#REF! | C39: =SUM(C40:C52) | E39: =SUM(E40:E52) | K39: =E39/C39-1 | L39: =E39*12
A40: Cartões para controle de acesso | C40: 70 | E40: 70 | K40: =E40/C40-1 | L40: =E40*12
A41: Chaveiro | C41: 50 | E41: 50 | K41: =E41/C41-1 | L41: =E41*12
A42: Lâmpadas | C42: 400 | E42: 300 | K42: =E42/C42-1 | L42: =E42*12
A43: Materiais/Serviços Obras Diversas (Alvenaria, Serralheria, Funilaria, Outros) | C43: 500 | E43: 500 | K43: =E43/C43-1 | L43: =E43*12
A44: Material de Ferragem (Elétrica, Hidráulica e Ferramentas) | C44: 1000 | E44: 1000 | K44: =E44/C44-1 | L44: =E44*12
A45: Material Expediente Interno | C45: 300 | E45: 300 | K45: =E45/C45-1 | L45: =E45*12
A46: Material Limpeza/Consumíveis | C46: 1200 | E46: 1500 | K46: =E46/C46-1 | L46: =E46*12
A47: Peças elevador | E47: 1400 | K47: =E47/C47-1 | L47: =E47*12
A48: Móveis e Utensílios | C48: 200 | E48: 300 | K48: =E48/C48-1 | L48: =E48*12
A49: Peças Ar Condicionado | C49: 1800 | E49: 1200 | K49: =E49/C49-1 | L49: =E49*12
A50: Peças de reposição para extintores e hidrantes e recargas eventuais | C50: 100 | E50: 100 | K50: =E50/C50-1 | L50: =E50*12
A51: Peças para Grupo Gerador, limpeza semestral filtro e óleo e óleo diesel | C51: 400 | E51: 400 | K51: =E51/C51-1 | L51: =E51*12
A52: Peças para manutenção das catracas | C52: 100 | E52: 270 | K52: =E52/C52-1 | L52: =E52*12
A54: DESPESAS ADMINISTRATIVAS | B54: =#REF!/#REF! | C54: =SUM(C55:C61) | D54: =C54/#REF! | E54: =SUM(E55:E61) | K54: =E54/C54-1 | L54: =E54*12
A55: Telefonia/Internet | C55: 400 | E55: 400 | K55: =E55/C55-1 | L55: =E55*12
A56: Impressões/Cópias | C56: 150 | E56: 165 | K56: =E56/C56-1 | L56: =E56*12
A57: Correio/Remessa Correspondências/Motoboy/Diversas | C57: 400 | E57: 400 | K57: =E57/C57-1 | L57: =E57*12
A58: Impostos - DIRF/DARF/ISSQN/PIS/COFINS | C58: 700 | E58: 700 | K58: =E58/C58-1 | L58: =E58*12
A59: Material Expediente APL | C59: =C14*0.1 | E59: =E14*0.1 | K59: =E59/C59-1 | L59: =E59*12
A60: Desepesas com Assembleia (Locação Cadeiras, Equipamentos) | C60: 100 | E60: 100 | K60: =E60/C60-1 | L60: =E60*12
A61: Custas Judiciais | C61: 100 | E61: 100 | K61: =E61/C61-1 | L61: =E61*12
A63: COTA 2018 / 2019 | B63: =SUM(B6,B20,B30,#REF!,B54) | C63: =SUM(C5,C19,C30,C39,C54) | E63: =SUM(E5,E19,E30,E39,E54) | K63: =E63/C63-1
A65: DESPESAS VARIÁVEIS (COBRADAS CONFORME CONSUMO MENSAL) | C65: =SUM(C66:C68) | E65: =SUM(E66:E68) | K65: =E65/C65-1 | L65: =E65*12
A66: Água e Esgoto - Área Comum | C66: 7000 | E66: 7100 | K66: =E66/C66-1 | L66: =E66*12
A67: Energia Elétrica - Área Comum | C67: 20000 | E67: 23895.5 | K67: =E67/C67-1 | L67: =E67*12
A68: Seguro fogo | C68: 13000 | E68: 13000 | K68: =E68/C68-1 | L68: =E68*12
A70: COTA 2018 | B70: =SUM(#REF!,B33,#REF!,B46,#REF!) | C70: 146647.94 | E70: =C71
A71: COTA 2019 | B71: =SUM(#REF!,B34,#REF!,B50,#REF!) | C71: =C63 | E71: =E63
A72: REAJUSTE PROPOSTO | B72: =SUM(#REF!,B35,#REF!,B52,#REF!) | C72: =(C71/C70)-1 | E72: =(E71/E70)-1
A74: REAJUSTE PROPOSTO COM MIGRAÇÃO DA LIMPEZA DE FACHADA | B74: =SUM(#REF!,B36,#REF!,B53,#REF!) | C74: 0.070816615 | E74: =(J74/E70)-1 | G74: 5000 | I74: 60000 | J74: =E71+G74
